{
  "key": "nba",
  "label": "NBA",
  "generated_at": "2026-06-24T07:03:32Z",
  "articles": [
    {
      "id": "ea43795de6c7cae8d59a5de0689032689739799470475ec8622dd2ddb20ff331",
      "title": "Lopez becomes NBA's 1st Mexico-born 1st-rounder",
      "url": "https://www.espn.com/nba/story/_/id/49161309/lopez-becomes-nba-1st-mexico-born-1st-rounder-traded-grizzlies",
      "source": "ESPN - NBA",
      "source_id": "espn_nba",
      "published_at": "2026-06-24T04:28:47Z",
      "summary": "Karim Lopez became the first player born in Mexico to be selected in the first round of the NBA draft, being selected with the No. 21 pick to the Detroit Pistons before being traded to the Memphis Grizzlies on Tuesday night.",
      "category": "nba",
      "image": null
    },
    {
      "id": "0cf923a1ff559ff026a1465e0071b89e51394464259ca5f012677b9f9c4b7307",
      "title": "Follow live: AJ Dybantsa selected No. 1, Jazz take...",
      "url": "https://www.espn.com/nba/draft/live",
      "source": "ESPN - NBA",
      "source_id": "espn_nba",
      "published_at": "2026-06-24T03:04:41Z",
      "summary": "Tune in to ABC and ESPN to watch how the first round of the NBA draft plays out.",
      "category": "nba",
      "image": null
    },
    {
      "id": "d636db3e0b40c1682e83b3c0812e231cfef0d60bf056e57b2f940cbcb58ec005",
      "title": "Johnson reunites with May, goes No. 9 to Mavs",
      "url": "https://www.espn.com/nba/story/_/id/49160374/johnson-reunites-mavs-leads-u-m-trio-draft-lottery",
      "source": "ESPN - NBA",
      "source_id": "espn_nba",
      "published_at": "2026-06-24T03:04:31Z",
      "summary": "The Mavericks picked Michigan forward Morez Johnson Jr. with the No. 9 pick, reuniting him with Dusty May less than six hours after he was announced as their new head coach.",
      "category": "nba",
      "image": null
    },
    {
      "id": "079c766df11ab2897a0441bf553baf9703584b898706bf5c6d20cb799834b0ea",
      "title": "Jayhawks' Peterson lands with Jazz at No. 2 pick",
      "url": "https://www.espn.com/nba/story/_/id/49159019/kansas-peterson-lands-jazz-no-2-pick-nba-draft",
      "source": "ESPN - NBA",
      "source_id": "espn_nba",
      "published_at": "2026-06-24T03:03:55Z",
      "summary": "Kansas guard Darryn Peterson, who had been considered a potential No. 1 pick, wound up with the Jazz as the second pick of the 2026 NBA draft.",
      "category": "nba",
      "image": null
    },
    {
      "id": "3b64382449a564eceadb0e1ba4e6703be64e5fe0a9ce05af030d8cbdb1af69f3",
      "title": "Hammon won't apologize, says Brunson 'outlier'",
      "url": "https://www.espn.com/nba/story/_/id/49157579/hammon-my-opinion-was-wrong-knicks-star-jalen-brunson",
      "source": "ESPN - NBA",
      "source_id": "espn_nba",
      "published_at": "2026-06-24T03:03:55Z",
      "summary": "Aces coach Becky Hammon had a change of heart regarding her prior criticism of Knicks star Jalen Brunson, saying Tuesday night that her \"opinion was wrong.\" But she's not apologizing for having it.",
      "category": "nba",
      "image": null
    },
    {
      "id": "02fe14ded6cf1246293bfe3f1ee8e2293b3b610def50d7d2c182bfe3b86698f5",
      "title": "Fantasy basketball: Julius Randle's trade to Brook...",
      "url": "https://www.espn.com/fantasy/basketball/story/_/id/49157117/fantasy-basketball-free-agent-trade-offseason-movement",
      "source": "ESPN - NBA",
      "source_id": "espn_nba",
      "published_at": "2026-06-24T01:35:15Z",
      "summary": "Andre Snellings and Eric Moody break down the fantasy impact of the latest offseason moves from around the NBA.",
      "category": "nba",
      "image": null
    },
    {
      "id": "390d2ff51e4740610009312cf6b6766da32fc1946ff0c0ad70c027c155e36002",
      "title": "Hammon won't apologize, says Brunson 'outlier'",
      "url": "https://www.espn.com/nba/story/_/id/49157579/hammon-not-apologizing-opinion-says-brunson-nba-outlier",
      "source": "ESPN - NBA",
      "source_id": "espn_nba",
      "published_at": "2026-06-23T23:27:05Z",
      "summary": "Aces coach Becky Hammon acknowledged Tuesday that Knicks star Jalen Brunson has put himself in a unique class of players, but didn't back off her general stance that small guards generally don't lead teams to NBA championships.",
      "category": "nba",
      "image": null
    },
    {
      "id": "073abc312b8a15f537353f0cd9f8e8b928e78f325723abf9094479a692bc986e",
      "title": "2026 NBA draft: Boozer, Dybantsa lead top fits from first round",
      "url": "https://www.espn.com/nba/story/_/id/49157116/2026-nba-draft-top-fashion-looks-fits-prospects",
      "source": "Currents API - Latest News",
      "source_id": "currents_latest_news",
      "published_at": "2026-06-23T22:59:27Z",
      "summary": "The NBA's next generation of players arrived in style for the 2026 draft in Brooklyn.",
      "category": "nba",
      "image": "https://a1.espncdn.com/combiner/i?img=%2Fphoto%2F2026%2F0623%2Fr1678431_1296x729_16%2D9.jpg"
    },
    {
      "id": "ba91eadca5d7dc8ea045805a1deba1308688b831cc1f49513c5e176997bbcf33",
      "title": "\"Trading a Ferrari for shopping cart\", \"Probably making $18/hr\" - NBA Fans Mock Trail Blazers For Micah Nori Hire Amid Tom Dundon's Cost-Cutting Era",
      "url": "https://www.sportskeeda.com/basketball/news-trading-ferrari-shopping-cart-probably-making-18-hr-nba-fans-mock-trail-blazers-for-micah-nori-hire-amid-tom-dundon-s-cost-cutting-era",
      "source": "Currents API - Latest News",
      "source_id": "currents_latest_news",
      "published_at": "2026-06-23T22:57:31Z",
      "summary": "On Tuesday, the Portland Trail Blazers named Micah Nori as their new head coach. Nori has been considered to be one of the best assistant coaches over the past few seasons.",
      "category": "nba",
      "image": "https://staticg.sportskeeda.com/editor/2026/06/34f25-17822537455690-1920.jpg"
    },
    {
      "id": "a0feb235d1fbac0c069adae755c583b595ff2ef6c4e78dcb4dcae2f1da4eca6f",
      "title": "Updated two-round mock draft: What we're hearing o...",
      "url": "https://www.espn.com/nba/story/_/id/49041464/2026-nba-mock-draft-projecting-60-picks-draft-night-trade-talks-boozer-peterson-dybantsa-acuff",
      "source": "ESPN - NBA",
      "source_id": "espn_nba",
      "published_at": "2026-06-23T17:10:01Z",
      "summary": "We have an updated 60-pick mock draft with new intel ahead of Round 1 of the 2026 NBA draft (Tuesday, 8 p.m. ET on ESPN/ABC).",
      "category": "nba",
      "image": null
    },
    {
      "id": "e5d475f598bede9fbb50065771b02086405d6bdbf57e2f7510a8a47796e1afc7",
      "title": "Bilas' top NBA draft prospects: Most talented, bes...",
      "url": "https://www.espn.com/nba/story/_/id/49100172/bilas-nba-draft-superlatives-no-1-pick-peterson-dybantsa-boozer-wilson-acuff",
      "source": "ESPN - NBA",
      "source_id": "espn_nba",
      "published_at": "2026-06-23T17:10:00Z",
      "summary": "Who should be No. 1? Who is the best guard after Darryn Peterson? Jay Bilas highlights 11 top prospects.",
      "category": "nba",
      "image": null
    },
    {
      "id": "0065d979ed9e619baade2b98dd1484daa9f4889ee232fac73caf75dcf08e2817",
      "title": "Latest NBA buzz: Everything we're hearing ahead of...",
      "url": "https://www.espn.com/nba/story/_/id/48377855/2026-nba-buzz-latest-live-updates-news-intel-nba-draft-offseason",
      "source": "ESPN - NBA",
      "source_id": "espn_nba",
      "published_at": "2026-06-23T17:04:33Z",
      "summary": "We're tracking the latest news, rumors and buzz across the NBA, including what we're hearing on the Giannis Antetokounmpo front.",
      "category": "nba",
      "image": null
    },
    {
      "id": "04135552738826ab4056514a2d5ea2b826c430e8fa671f5f10eed87d4e0753a3",
      "title": "Grading big NBA trades: Why did the Thunder send A...",
      "url": "https://www.espn.com/nba/story/_/id/49135150/2026-nba-offseason-trade-grades-contracts-new-deals-rosters-teams",
      "source": "ESPN - NBA",
      "source_id": "espn_nba",
      "published_at": "2026-06-23T17:04:33Z",
      "summary": "We're grading the biggest NBA trades of the offseason, including the three-team deal that saw Julius Randle land in Brooklyn.",
      "category": "nba",
      "image": null
    },
    {
      "id": "03219ae27194b10da525c3dd4a99b851154c9d52fb2623717fd6680cfdcc8360",
      "title": "Sources: Randle off to Nets as part of 3-team deal...",
      "url": "https://www.espn.com/nba/story/_/id/49149223/sources-wolves-trade-randle-nets-claxton-bulls",
      "source": "ESPN - NBA",
      "source_id": "espn_nba",
      "published_at": "2026-06-23T16:57:35Z",
      "summary": "The Timberwolves are sending Julius Randle and the No. 28 pick in the NBA draft to the Nets as part of a three-team trade that also will see Nic Claxton go to the Bulls and Minnesota get the No. 33 pick from Brooklyn, sources told ESPN's Shams Charania.",
      "category": "nba",
      "image": null
    },
    {
      "id": "94cedc1c8f5a9e55a22debb2b8219cca711c1fd5e556aac86e41c53679175442",
      "title": "Golden Knights owner launching NBA Vegas bid",
      "url": "https://www.espn.com/nhl/story/_/id/49147109/golden-knights-owner-bill-foley-launching-nba-las-vegas-bid",
      "source": "ESPN - NBA",
      "source_id": "espn_nba",
      "published_at": "2026-06-23T16:57:35Z",
      "summary": "Golden Knights founder and majority owner Bill Foley announced Monday that he is launching a bid to bring an NBA franchise to Las Vegas.",
      "category": "nba",
      "image": null
    },
    {
      "id": "3cd3ded3bca6533f2510d2f8ee0eae8e02a29bf5770a90ffb17efa56d27678e0",
      "title": "Sources: Thunder to ship Wiggins to Hawks for pick...",
      "url": "https://www.espn.com/nba/story/_/id/49141113/sources-hawks-land-aaron-wiggins-trade-thunder",
      "source": "ESPN - NBA",
      "source_id": "espn_nba",
      "published_at": "2026-06-23T16:57:35Z",
      "summary": "The Atlanta Hawks are finalizing a deal to acquire Aaron Wiggins from the Oklahoma City Thunder for two second-round draft picks, sources told ESPN's Shams Charania on Sunday.",
      "category": "nba",
      "image": null
    },
    {
      "id": "f0a9d0782ae667540dc3fd3a9d2fb2c0b60af11ab0701f24c54a691b932ebfe4",
      "title": "\ud83d\udc40 Where are the 2016 Cleveland Cavaliers now?",
      "url": "https://www.espn.com/nba/story/_/id/49113154/the-10-year-anniversary-greatest-2016-nba-finals-history-cleveland-cavaliers-golden-state-warriors-lebron-james-kyrie-irving-stephen-curry",
      "source": "ESPN - NBA",
      "source_id": "espn_nba",
      "published_at": "2026-06-23T16:57:35Z",
      "summary": "From LeBron to Kyrie to Timofey Mozgov, here's where those 2016 Cavaliers are now -- a decade after the most epic comeback ever.",
      "category": "nba",
      "image": null
    },
    {
      "id": "4bb998acf810003e9ddd006dedb7a2aaafe57e38bb3d8f6aba3eb34d39fa086a",
      "title": "Grades for both sides of the Giannis trade: Winner...",
      "url": "https://www.espn.com/nba/story/_/id/49112635/giannis-antetokounmpo-trade-grades-winners-losers-reaction-bucks-heat",
      "source": "ESPN - NBA",
      "source_id": "espn_nba",
      "published_at": "2026-06-23T15:49:22Z",
      "summary": "The Bucks sent star Giannis Antetokounmpo to Miami. Which side won the trade?",
      "category": "nba",
      "image": null
    },
    {
      "id": "10461854a51e9029ef5049cc14333594f36704bce40189eef1219abd39e2f0cd",
      "title": "Giannis traded to Heat: Everything we know about t...",
      "url": "https://www.espn.com/nba/story/_/id/49144931/giannis-traded-heat-faq-blockbuster-move-means-bucks-celtics-draft-playoff-race",
      "source": "ESPN - NBA",
      "source_id": "espn_nba",
      "published_at": "2026-06-23T15:49:22Z",
      "summary": "How does Miami build around Giannis and Bam? What's next in Milwaukee?",
      "category": "nba",
      "image": null
    },
    {
      "id": "83d5efb922246cc536a734fe9c6bef601c5a3f7513967e177ad096f2b3f47c61",
      "title": "Tyler Herro among biggest beneficiaries of Giannis...",
      "url": "https://www.espn.com/fantasy/basketball/story/_/id/49153198/giannis-antetokounmpo-trade-reaction-fantasy-basketball-heat-bucks",
      "source": "ESPN - NBA",
      "source_id": "espn_nba",
      "published_at": "2026-06-23T15:32:56Z",
      "summary": "The first big move of the NBA offseason could be a positive for many players in fantasy.",
      "category": "nba",
      "image": null
    },
    {
      "id": "e49e61cb19e2c76d9d5c2c6fd2f703ee668b5708d44909ab5e4915389b1a002a",
      "title": "First overall, first in fashion: No. 1 NBA draft l...",
      "url": "https://www.espn.com/nba/story/_/id/40424508/nba-draft-top-pick-fashion-wembanyama-lebron",
      "source": "ESPN - NBA",
      "source_id": "espn_nba",
      "published_at": "2026-06-23T14:42:23Z",
      "summary": "From Paolo Banchero's purple suit and \"P5\" chain to LeBron James' all-white look, fashion statements for NBA top draft picks have evolved greatly over the years.",
      "category": "nba",
      "image": null
    },
    {
      "id": "6c4edd2937b9002493c47527d1efff16a006b272c9169012768caad113054f1e",
      "title": "Grades for every NBA free agent signing: Suns, Haw...",
      "url": "https://www.espn.com/nba/story/_/id/48957095/2026-nba-free-agency-grades-offseason-signings-deals-contracts-extensions-depth-charts",
      "source": "ESPN - NBA",
      "source_id": "espn_nba",
      "published_at": "2026-06-23T13:59:05Z",
      "summary": "We're grading the biggest NBA free agent signings and extensions, including Ayo Dosunmu's new deal with the Timberwolves.",
      "category": "nba",
      "image": null
    },
    {
      "id": "3e13c9ddda848d4d6e45376614d2d55121cadb1eb43ab1e32646dbf0746a2abf",
      "title": "NBA trade tracker: Thunder send Aaron Wiggins to H...",
      "url": "https://www.espn.com/nba/story/_/id/48957844/nba-trade-tracker-details-every-deal-2026-offseason-draft-free-agency",
      "source": "ESPN - NBA",
      "source_id": "espn_nba",
      "published_at": "2026-06-23T13:59:05Z",
      "summary": "We have the details, including players and draft picks, for every NBA trade made this summer.",
      "category": "nba",
      "image": null
    },
    {
      "id": "e242a78cb3dd23ed6209ee4fe62710070c8cd6d4cac5da20f3fa408bbef481ef",
      "title": "Sources: Heat land Giannis in blockbuster trade",
      "url": "https://www.espn.com/nba/story/_/id/49149967/bucks-trading-giannis-antetokounmpo-bobby-portis-heat-tyler-herro-kelel-ware-jaime-jaquez-jr-kasparas-jakucionis-picks",
      "source": "ESPN - NBA",
      "source_id": "espn_nba",
      "published_at": "2026-06-23T03:52:00Z",
      "summary": "The Bucks are trading Giannis Antetokounmpo and Bobby Portis to the Heat for Tyler Herro, Kel'el Ware, Jaime Jaquez Jr., Kasparas Jakucionis, three first-round picks (including No. 13 in Tuesday's draft), one pick swap and one second-rounder, per sources.",
      "category": "nba",
      "image": null
    },
    {
      "id": "441d8e4600e1dad096fa440dc513ac284fe345f5df53f5fb09a16a506d9567e8",
      "title": "How the Knicks and hip-hop united New York",
      "url": "https://www.espn.com/nba/story/_/id/49129951/knicks-new-york-rap-nba-finals-parade",
      "source": "ESPN - NBA",
      "source_id": "espn_nba",
      "published_at": "2026-06-22T19:58:15Z",
      "summary": "The last time the Knicks won a title, hip-hop was born. Fifty-three years later, New York's rappers took a victory lap.",
      "category": "nba",
      "image": null
    },
    {
      "id": "0c6cde5e8f492ed659b71b3b68eef5ff207f078eff0f0a8d1ba8ad70564c5a8a",
      "title": "Sources: U-M's May finalizing deal to coach Mavs",
      "url": "https://www.espn.com/nba/story/_/id/49143856/sources-michigan-dusty-finalizing-deal-coach-mavericks",
      "source": "ESPN - NBA",
      "source_id": "espn_nba",
      "published_at": "2026-06-22T14:19:00Z",
      "summary": "Michigan coach Dusty May is finalizing a deal to take the Dallas Mavericks' head coaching job, sources told ESPN, an axis-shifting move that significantly alters the college and NBA landscapes.",
      "category": "nba",
      "image": null
    }
  ]
}
