{
  "key": "stocks",
  "label": "Stocks",
  "generated_at": "2026-07-08T12:19:05Z",
  "articles": [
    {
      "id": "08bd296f49b87c8f4e830f87701e54c4aeb1a98aaaf00bffa683a9c0038e0337",
      "title": "DTE Energy Co. highlights regulated utility growth while supporting Michigan's transition",
      "source": "Alpha Vantage - NEWS_SENTIMENT",
      "source_id": "alphavantage_news_sentiment",
      "published_at": "2026-07-08T11:07:47Z",
      "summary": "DTE Energy Co., a major regulated utility in Michigan, is focusing on infrastructure investment, cleaner generation, and stable cash flows to drive long-term growth for shareholders and customers. The company's strategy includes transitioning to cleaner energy sources, investi...",
      "content": "<p>DTE Energy Co. (ISIN US2333311072) is a diversified energy company based in Detroit, Michigan, with a core focus on regulated electric and gas utility operations and related infrastructure services in the United States. The company plays a central role in delivering power and natural gas to residential, commercial and industrial customers across its service territory, aiming for reliability, safety and increasingly cleaner energy. For investors, the combination of regulated earnings, long-term capital plans and an evolving generation mix toward lower emissions is a significant part of the long-run equity story.</p> <h2>Regulated utility foundation</h2> <p>At the heart of DTE Energy Co.'s business model is its regulated electric utility, which owns and operates generation assets, transmission lines and distribution networks that bring electricity to customers under state oversight of rates and investment plans. The regulated framework generally allows the company to earn an approved return on equity on prudently incurred infrastructure spending, such as grid modernization, storm hardening and the replacement of aging equipment. This structure can support relatively predictable cash flows and earnings, subject to regulatory decisions and demand trends.</p> <p>DTE Energy Co. also operates a regulated natural gas utility that delivers gas through an extensive pipeline and distribution system, supplying heat and fuel to households and businesses throughout its service area. The gas utility similarly earns returns on approved investments, including pipeline modernization, system integrity programs and safety initiatives. These regulated operations are typically aligned with state energy policy goals, such as reliability, affordability and emissions reduction, and they often involve multi-year plans for capital expenditure that extend visibility for management and investors.</p> <h2>Strategic focus on cleaner energy</h2> <p>Over recent years, DTE Energy Co. has described a strategy centered on transitioning its generation portfolio toward cleaner sources while maintaining grid reliability. This has involved retiring or reducing reliance on older coal-fired plants, adding natural gas capacity as a bridge fuel and expanding renewable energy assets such as wind and solar projects across Michigan. The company has highlighted long-term decarbonization targets that align with state policy and broader industry trends, which may include interim milestones for carbon reductions and timelines for coal retirements.</p> <p>In addition to utility-scale renewables, DTE Energy Co. has invested in programs that enable customers to participate in voluntary green energy offerings, such as renewable subscription products or green pricing plans. These initiatives can help large commercial and industrial customers meet their sustainability commitments, while residential customers can opt to match a portion of their usage with renewable generation. The company also invests in energy efficiency programs, demand-response initiatives and advanced metering infrastructure that support more flexible and efficient use of electricity and gas.</p> <h2>Diversified business segments</h2> <p>Beyond its core regulated utilities, DTE Energy Co. has historically maintained a portfolio of non-utility businesses and segments that provide earnings diversification and exposure to different parts of the energy value chain. These activities can include midstream gas operations, such as gathering, processing and pipeline transportation of natural gas, often serving producers and markets in various regions of the United States. Midstream assets can be underpinned by long-term contracts and fee-based arrangements, although they are subject to commodity-cycle dynamics and regional production trends.</p> <p>The company has also engaged in power and industrial projects that deliver energy-related services to large customers, such as on-site generation, waste-to-energy solutions or customized energy management offerings. These projects typically rely on structured contracts, providing predictable revenue streams while helping customers manage costs and environmental goals. Over time, DTE Energy Co. has made portfolio adjustments, acquiring or divesting assets to align with its strategic priorities, risk appetite and capital allocation plans. For investors, the mix between regulated and non-regulated businesses influences the company's overall risk profile and growth trajectory.</p> <h2>Representative customer programs</h2> <p>A representative example of DTE Energy Co.'s customer-facing offerings is its portfolio of residential and small-business energy efficiency programs. Through these initiatives, the company encourages customers to adopt more efficient appliances, lighting, heating and cooling equipment, offering rebates, incentives and educational support. Such programs can reduce overall demand growth, ease strain on the grid during peak periods and help customers lower their bills, while also contributing to state and company goals for emissions reduction.</p> <p>DTE Energy Co. has also promoted home energy audits, smart thermostats and digital tools that give customers more visibility into their usage patterns. By combining advanced metering infrastructure with online portals and mobile applications, the company enables customers to track consumption, receive alerts and make informed decisions about shifting usage away from high-cost peak hours. These offerings exemplify how a traditional utility can leverage technology to enhance customer engagement, support conservation and manage system resources more effectively.</p> <h2>DTE Energy stock and market context</h2> <p>DTE Energy Co. is listed on a major U.S. stock exchange and its shares trade in U.S. dollars, reflecting its status as a large domestic utility with a predominantly U.S. customer base. The stock is often compared with other regulated utility names that feature similar characteristics, such as stable dividends, long-lived infrastructure assets and sensitivity to interest rates and regulatory decisions. Market participants commonly evaluate the company using metrics like earnings per share, rate base growth, capital expenditure plans and leverage ratios.</p> <p>Because utility stocks are often viewed as income-oriented holdings, DTE Energy Co.'s dividend policy and track record of payments and increases are important components of its equity appeal. Investors also pay attention to the company's credit ratings and access to capital markets, given the ongoing need to fund large-scale investments in generation, transmission, distribution and gas infrastructure. While the share price can fluctuate in response to broader market moves, interest rate changes and sector rotation, many investors focus on long-term fundamentals, regulatory outcomes and execution on strategic projects.</p> <p>Disclaimer zu unseren Artikeln: Keine Anlageberatung, keine Kauf oder Verkaufsempfehlung. Angaben zu Kursen, Unternehmen und M\u00e4rkten ohne Gew\u00e4hr; \u00c4nderungen jederzeit m\u00f6glich. B\u00f6rsengesch\u00e4fte k\u00f6nnen zu hohen Verlusten f\u00fchren. Unsere Beitr\u00e4ge werden ganz oder teilweise automatisiert mit Unterst\u00fctzung von AI erstellt und gepr\u00fcft.</p>",
      "category": "stocks",
      "image": null
    },
    {
      "id": "49333dd984b27f186cec2ba80406e324b383208c074a5693812b8be14f658de3",
      "title": "Alphabet slides premarket as Google AI costs meet cloud headwinds",
      "source": "Alpha Vantage - NEWS_SENTIMENT",
      "source_id": "alphavantage_news_sentiment",
      "published_at": "2026-07-08T11:07:09Z",
      "summary": "Alphabet Inc. (NASDAQ:GOOGL) shares slid premarket due to concerns over high AI spending and cloud headwinds, with the company projecting significant capital expenditures for 2026. Investors are scrutinizing whether Google's AI investments will yield sufficient returns to just...",
      "content": "<p>Alphabet Inc. (NASDAQ:GOOGL) shares slid premarket due to concerns over high AI spending and cloud headwinds, with the company projecting significant capital expenditures for 2026. Investors are scrutinizing whether Google&#x27;s AI investments will yield sufficient returns to justify the costs, especially as its valuation no longer presents a significant discount compared to peers like Amazon and NVIDIA. Despite analyst backing and its recent inclusion in the Dow, the market is weighing funding pressure against the potential for AI returns, with some analysts suggesting a rotation into AI hyperscalers but noting a lack of clear evidence of strong AI product returns.</p>",
      "category": "stocks",
      "image": null
    },
    {
      "id": "760379ebe3620e8f3e93122feb90969df59ea06c356f6a1089b8d017c194a9d7",
      "title": "Microchip drops license fees for MPLAB tools, including machine learning suite",
      "source": "Alpha Vantage - NEWS_SENTIMENT",
      "source_id": "alphavantage_news_sentiment",
      "published_at": "2026-07-08T11:03:30Z",
      "summary": "Microchip Technology has announced that its MPLAB XC Pro Compilers and MPLAB Machine Learning Development Suite are now available to developers at no cost and with unlimited installs. This move aims to remove barriers to innovation, enabling free access to advanced optimizatio...",
      "content": "<h2>Microchip Expands Developer Access with Free MPLAB\u00ae XC Compilers and MPLAB Machine Learning Development Suite</h2> <h2>Rhea-AI Summary</h2> <p>Microchip (Nasdaq:MCHP) is making its MPLAB XC Pro Compilers and MPLAB Machine Learning Development Suite available at no cost, with unlimited installs for individuals and teams. These tools support optimized embedded code and integrated ML workflows across Microchip\u2019s 8-, 16- and 32-bit MCU/MPU portfolio.</p> <p>T\u00dcV S\u00dcD\u2011certified MPLAB XC Functional Safety Compilers are also now free to download, with paid certification documentation and support available when needed. Updates and priority technical support are included at no additional charge.</p> <p>AI-generated analysis. How Rhea-AI works. Not financial advice.</p> <h3>Positive</h3> <ul> <li>None.</li> </ul> <h3>Negative</h3> <ul> <li>None.</li> </ul> <h3>Key Figures</h3> <h3>Previous AI Reports</h3> Date Event Sentiment 24h Move Catalyst Jun 02 AI retimer launch Positive +5.9% Introduced PCIe 6.0 and CXL 3.1 retimers targeting AI data centers. May 26 SiC power modules Positive +4.9% Launched 3.3 kV SiC power modules for AI data center power and SSTs. Apr 23 timing modules launch Positive +9.9% Released plug-in timing modules for data centers and 5G networks supporting AI loads. Apr 14 dsPIC33A expansion Positive +1.3% Expanded dsPIC33A DSC family aimed at AI data center power and intelligent sensing. Feb 10 edge AI solutions Positive +3.3% Unveiled production-ready full-stack edge AI solutions using MCUs, MPUs and FPGAs. <p>24h Move is the share-price change in the day after each event; other market factors may also have contributed.</p> <p>Recent AI-tag announcements have all been followed by positive next-day moves, averaging about 5.07%.</p> <h3>Historical Comparison</h3> <p>Across five prior AI-tag announcements, the stock typically reacted with moves near 5.07%. This tools-focused AI update fits that pattern of product-centered AI news rather than marking a clear break from it.</p> <h3>Regulatory &amp; Risk Context</h3> <p>Reported short interest appears relatively low, suggesting limited short-squeeze potential and a more fundamentals-driven trading profile rather than one dominated by crowded bearish positioning.</p> <h3>Key Terms</h3> <h3>embedded machine learning technical</h3> <h3>microcontroller technical</h3> <h3>microprocessor technical</h3> <h3>functional safety technical</h3> <p>AI-generated analysis. How Rhea-AI works. Not financial advice.</p> <p>Unlimited installs and built-in optimization tools support simplified, accelerated embedded and edge AI deployment</p> <p>CHANDLER, Ariz., July 08, 2026 (GLOBE NEWSWIRE) -- Microchip Technology (Nasdaq: MCHP) has announced that its MPLAB\u00ae XC Pro Compilers and MPLAB Machine Learning (ML) Development Suite are now available at no cost to customers. By enabling unlimited installs across individual and team environments, these tools give developers free access to advanced optimization capabilities and integrated embedded machine learning workflows.</p> <p>\u201cOur focus is on optimizing the development experience for engineers using Microchip devices,\u201d said Greg Robinson, corporate vice president of Microchip\u2019s development tools, MCU and wireless business units. \u201cBy eliminating license fees and providing high-performance tools at no cost, we\u2019re removing barriers to innovation. Customers can now take advantage of our optimized compilers and integrated machine learning capabilities to move efficiently from design through deployment.\u201d</p> <p>Previously available through paid license tiers, the MPLAB XC Pro Compilers apply high-level techniques to reduce code size, lower the memory footprint, improve execution speed and generate highly efficient, architecture\u2011optimized code for embedded applications. These professional-grade capabilities enable developers to streamline embedded design across Microchip\u2019s 8-, 16- and 32-bit microcontroller (MCU) and microprocessor (MPU) portfolio.</p> <p>The MPLAB Machine Learning Development Suite Model Builder, an MPLAB or Microsoft\u00ae Visual Studio\u00ae Code (VS Code\u00ae) plug-in used to generate optimized AI and IoT sensor recognition code, is also available at no cost. This allows developers to build and deploy end-to-end embedded machine learning solutions and helps enable efficient deployment of edge intelligence on resource\u2011constrained devices. By offering MPLAB ML in VS Code, Microchip is furthering its commitment to meeting developers in their environment of choice, providing a more flexible and easier\u2011to\u2011use development experience.</p> <p>The shift to offer free development tools extends to Microchip\u2019s MPLAB XC Functional Safety Compilers. T\u00dcV S\u00dcD\u2011certified, these compilers support safety\u2011critical applications and help enable compliance with industry functional safety standards, with certification documentation and support available for purchase when needed. With the free download, developers can now begin safety-oriented design without upfront license costs and fees applied only when certification is required.</p> <p>Updates and priority technical support for compiler-related queries are included at no additional cost. Visit the website for more information about Microchip\u2019s full suite of VS Code extensions.</p> <p>Pricing and Availability<br>MPLAB XC Compilers and the MPLAB Machine Learning Development Suite are available at no cost. For more information, contact a Microchip sales representative or authorized worldwide distributor.</p> <p>Resources<br>High-res images available through Flickr or editorial contact (feel free to publish):<br>Application image: https://www.flickr.com/gp/microchiptechnology/L08dD49mKm</p> <p>About Microchip Technology:<br>Microchip Technology Inc. is a broadline supplier of semiconductors committed to making innovative design easier through total system solutions that address critical challenges at the intersection of emerging technologies and durable end markets. Its easy-to-use development tools and comprehensive product portfolio supports customers throughout the design process, from concept to completion. Headquartered in Chandler, Arizona, Microchip offers outstanding technical support and delivers solutions across the industrial, automotive, consumer, aerospace and defense, communications and computing markets. For more information, visit the Microchip website at www.microchip.com. </p> <p>Note: The Microchip name and logo, the Microchip logo and MPLAB are registered trademarks of Microchip Technology Incorporated in the U.S.A. and other countries. All other trademarks mentioned herein are the property of their respective companies.</p> <p>Editorial Contact:<br>Amber Liptai<br>480-792-5047<br>amber.liptai@microchip.com</p>",
      "category": "stocks",
      "image": null
    },
    {
      "id": "3a72d6678a63548f337672d635d9726bb86164af59a79a1b6db11bdf8588bb69",
      "title": "Microsoft layoff: Employees offered up to 39 weeks' pay, stock vesting; here's who gets what",
      "source": "LiveMint \u2014 Companies",
      "source_id": "livemint_companies",
      "published_at": "2026-07-08T11:03:25Z",
      "summary": "Microsoft announced layoffs affecting 4,800 employees, offering severance packages up to 39 weeks' pay. Compensation varies by employee level, with options for continued stock vesting and health insurance. The cuts aim to streamline costs amid significant AI investments.",
      "content": "<p>After announcing on Monday that it would lay off around 4,800 employees (or 2.1% of its global workforce), Microsoft said the affected workers would receive severance packages of up to 39 weeks' base pay, according to a Business Insider report.</p> <p>Microsoft's severance package varies by employee level, the report stated. Those working at internal levels 64 and below will receive one week of base pay for every six months of service, while those at levels 65 to 67 will receive two weeks of base pay for the same period.</p> <p>Executives at level 68 and above will have a different compensation plan.</p> <p>In addition to severance pay, eligible employees at levels 67 and below will continue to receive regular stock vesting for six or 12 months, depending on their tenure. The company will also provide 6 months of paid health insurance, with the option to extend coverage for an additional 12 months through COBRA.</p> <p>Those terms are similar to those the company offered earlier this year in its Voluntary Retirement Program buyouts, the Business Insider report revealed</p> <p></p> <p>The job cuts come as Microsoft looks to streamline costs while continuing to invest heavily in growth. The company is expected to spend about $190 billion in capital expenditures this year, primarily on expanding artificial intelligence infrastructure.</p> <p>The cuts include the deepest overhaul in Xbox's history, with approximately 3,200 gaming jobs to be shed over the coming fiscal year, four game studios being spun off or sold, and a fifth entering a review process that could lead to closure, the company said.</p> <p>\"Our business is changing because the world around it is changing,\" Amy Coleman, Microsoft's executive vice president, wrote in a memo to all employees.</p> <p>\"Companies don't get to choose whether their industry changes; they only get to choose whether they change with it.\"</p> <p>The announcement is the latest in a string of mass layoffs by the technology giant as it spends massive amounts of money to stay in the artificial intelligence race, with companies investing tens of billions of dollars in AI-ready data centers and computing power.</p> <p>The US severance package includes a minimum of 60 days of base pay during which employees remain on the payroll, up to a maximum of 39 weeks for most employees, based on seniority and tenure.</p> <p>Salesforce, which recently conducted layoffs, has a standard severance package of a minimum of nine weeks and a maximum of 30 weeks of base pay. Oracle offered laid-off US employees four weeks' base salary, plus one week per additional year of employment, up to 26 weeks, as severance.</p> <p>Sanchari Ghosh is an Assistant Editor at Mint with over 12 years of experience in journalism, specialising in personal finance, DLT &amp; DeFi, geopolitics and foreign policy, with a particular emphasis on how these areas intersect. &lt;br&gt; She writes extensively about how money works in everyday life\u2014helping readers navigate personal finance decisions. &lt;br&gt; As AI reshapes investing behaviour, capital is increasingly flowing into decentralized ecosystems, redefining how assets are managed, traded, and valued. She focuses on explaining how money flows within frameworks like Distributed Ledger Technology (DLT), DeFi protocols, and crypto markets\u2014while also exploring what the future of money could look like in a trustless, programmable financial world. &lt;br&gt; She also focuses on immigration-related issues, simplifying complex topics around visas, passports, overseas financial planning, and the many practical challenges Indians face while moving or living abroad. &lt;br&gt; Alongside personal finance, Sanchari has a strong understanding of international politics, contemporary and historical conflicts, and global state decisions. She closely tracks how geopolitical developments influence economies, markets, and individual financial choices, bringing together finance and global affairs in her reporting. &lt;br&gt; She began her career as a desk editor, which gave her a strong foundation in news writing. Over time, her interest naturally shifted toward personal finance. Before joining Mint in 2020, she worked DNA, The Times of India, Outlook Money, BloombergQuint, and ETMoney. At Mint, she got an opportunity to expand her coverage to include immigration and geopolitical developments while continuing to closely follow personal finance trends and market movements.As a journalist, she is committed to accuracy, intellectual rigour, and fairness. &lt;br&gt; She is an English Major and her work took her across cities including Delhi, Mumbai, and Pune. Living independently from an early age gave her firsthand experience in managing life and money on her own. This practical exposure sparked her strong interest in personal finance. &lt;br&gt; Outside the newsroom, Sanchari is a sports enthusiast who regularly plays lawn tennis and squash. In her younger years, she was also a national-level badminton player.</p>",
      "category": "stocks",
      "image": "https://www.livemint.com/lm-img/img/2026/07/08/1600x900/logo/MICROSOFT-AI--0_1783508039972_1783508082105_3ca71d1e-bbc4-4e32-99ff-fd7241a3752f.JPG"
    },
    {
      "id": "318ecbd8065e3afbf898eb806d83502df8bda488222312d4c88233017da5a934",
      "title": "Keefe, Bruyette & Woods Adjusts Price Target on Jack Henry & Associates to $200 From $205",
      "source": "Alpha Vantage - NEWS_SENTIMENT",
      "source_id": "alphavantage_news_sentiment",
      "published_at": "2026-07-08T11:00:25Z",
      "summary": "Keefe, Bruyette & Woods has adjusted its price target for Jack Henry & Associates (JKHY) down to $200 from $205. The financial services technology provider is actively engaged in collaborations, including an expanded partnership with Google Cloud for AI-driven security and has...",
      "content": "<p>This super rating is the result of a weighted average of the rankings based on the following ratings: Valuation (Composite), EPS Revisions (4 months), and Visibility (Composite). We recommend that you carefully review the associated descriptions.</p> <p>Investor</p> <p>This super composite rating is the result of a weighted average of the rankings based on the following ratings: Fundamentals (Composite), Valuation (Composite), EPS Revisions (1 year), and Visibility (Composite). We recommend that you carefully review the associated descriptions.</p> <p>Global</p> <p>This composite rating is the result of an average of the rankings based on the following ratings: Fundamentals (Composite), Valuation (Composite), Financial Estimates Revisions (Composite), Consensus (Composite) and Visibility (Composite). The company must be covered by at least 4 of these 5 ratings for the calculation to be carried out. We recommend that you carefully review the associated descriptions.</p> <p>Quality</p> <p>This composite rating is the result of an average of rankings based on the following ratings: Returns (Composite), Profitability (Composite) and Quality of Financial Reporting (Composite), and Financial Health (Composite). The company must be covered by at least 2 of these 3 ratings for the calculation to be performed. We recommend that you carefully read the associated descriptions.</p> <p>ESG MSCI</p> <p>The MSCI ESG score assesses a company\u2019s environmental, social, and governance practices relative to its industry peers. Companies are rated from CCC (laggard) to AAA (leader). This rating helps investors incorporate sustainability risks and opportunities into their investment decisions.</p>",
      "category": "stocks",
      "image": null
    },
    {
      "id": "5dc5c4710ecaaa9943c5f0c95df5753d5183050545b77d1e965da8dc70b581dd",
      "title": "Moderna adds former Biogen CFO Michael McDonnell to its board",
      "source": "Alpha Vantage - NEWS_SENTIMENT",
      "source_id": "alphavantage_news_sentiment",
      "published_at": "2026-07-08T11:00:23Z",
      "summary": "Moderna (NASDAQ: MRNA) has appointed Michael McDonnell, former CFO of Biogen, to its Board of Directors, effective July 8, 2026. He will also serve on the Board\u2019s Audit Committee, bringing over 35 years of financial leadership experience in the life sciences and technology sec...",
      "content": "<h2>Moderna Appoints Michael McDonnell to Board of Directors</h2> <h2>Rhea-AI Summary</h2> <p>Moderna (NASDAQ:MRNA) appointed Michael McDonnell to its Board of Directors, effective July 8, 2026. He will also serve on the Board\u2019s Audit Committee.</p> <p>McDonnell brings over 35 years of financial leadership, including CFO roles at Biogen, IQVIA, Intelsat, MCG Capital and EchoStar, plus advisory work with Goldman Sachs Asset Management and board service at Merit Medical Systems and Baxter International.</p> <p>AI-generated analysis. How Rhea-AI works. Not financial advice.</p> <h3>Positive</h3> <ul> <li>Adds board member with 35+ years of financial leadership experience</li> <li>Former Biogen CFO joins and will serve on Audit Committee</li> <li>Extensive life sciences and technology sector background supports Moderna\u2019s pipeline execution</li> <li>Experience overseeing capital allocation and investor relations strengthens financial governance</li> </ul> <h3>Negative</h3> <ul> <li>None.</li> </ul> <p>Former Biogen Chief Financial Officer brings more than 35 years of financial leadership and public company experience</p> <p>CAMBRIDGE, MA / ACCESS Newswire / July 8, 2026 / Moderna, Inc. (NASDAQ:MRNA) today announced the appointment of Michael McDonnell to its Board of Directors, effective July 8, 2026. Mr. McDonnell will also serve on the Board's Audit Committee.</p> <p>\"Mike brings exceptional financial leadership and strategic perspective developed over more than three decades advising and leading global life sciences and technology companies,\" said Noubar Afeyan, Ph.D., Co-Founder and Chairman of Moderna. \"His experience guiding organizations through periods of growth and transformation, overseeing significant capital allocation decisions, and building high-performing finance organizations will be invaluable as Moderna continues to advance its pipeline and execute on its long-term strategy. We are pleased to welcome Mike to our Board.\"</p> <p>\"I am honored to join Moderna's Board at such an important time in the company's evolution,\" said Mr. McDonnell. \"Moderna has established itself as a leader in mRNA science and innovation, with a broad pipeline and a compelling long-term vision. I look forward to working with the Board and management team to help create lasting value for patients and shareholders.\"</p> <p>\"We are delighted to welcome Mike to Moderna's Board,\" said St\u00e9phane Bancel, Chief Executive Officer of Moderna. \"His extensive experience as CFO of leading public companies, deep understanding of the biotechnology industry, and proven ability to lead complex strategic and operational initiatives will be an important asset as we prepare for multiple potential product launches and build Moderna for the long term.\"</p> <p>Mr. McDonnell is a financial executive with substantial experience providing financial and accounting leadership to life sciences and technology companies, including more than 24 years serving as chief financial officer of public companies.</p> <p>Most recently, Mr. McDonnell served as Executive Vice President and Chief Financial Officer of Biogen Inc. from August 2020 through February 2025, where he oversaw investor relations, financial planning and analysis, treasury, accounting, tax, internal audit, procurement, information technology, and business unit finance. Since March 2025, he has served as an advisor to Goldman Sachs Asset Management.</p> <p>Prior to Biogen, Mr. McDonnell served as Executive Vice President and Chief Financial Officer of IQVIA Holdings Inc. following the merger of Quintiles and IMS Health. Earlier in his career, he served as Executive Vice President and Chief Financial Officer of Intelsat S.A., Executive Vice President and Chief Financial Officer of MCG Capital Corporation, and Chief Financial Officer of EchoStar Communications Corporation. He began his career at PricewaterhouseCoopers LLP, where he spent 14 years, including four years as a partner.</p> <p>Mr. McDonnell currently serves on the Board of Directors of Merit Medical Systems, Inc., where he chairs the Audit Committee, and on the Board of Directors of Baxter International Inc. He previously served on the Board of Directors of Catalyst Health Solutions until its acquisition.</p> <p>About Moderna</p> <p>Moderna is a pioneer and leader in the field of mRNA medicine. Through the advancement of its technology platform, Moderna is reimagining how medicines are made to transform how we treat and prevent diseases. Since its founding, Moderna's mRNA platform has enabled the development of vaccines and therapeutics across infectious diseases, cancer, rare diseases and more.</p> <p>With a global team and a unique culture, driven by the company's values and mindsets, Moderna's mission is to deliver the greatest possible impact to people through mRNA medicines. For more information about Moderna, please visit modernatx.com and connect with us on X, Facebook, Instagram, YouTube and LinkedIn.</p> <p>Forward-Looking Statements</p> <p>This press release contains forward-looking statements within the meaning of the Private Securities Litigation Reform Act of 1995, as amended, including statements regarding: Moderna's ability to advance its pipeline and execute on its long-term strategy; and expectations for multiple potential product launches. The forward-looking statements in this press release are neither promises nor guarantees, and you should not place undue reliance on these forward-looking statements because they involve known and unknown risks, uncertainties, and other factors, many of which are beyond Moderna's control and which could cause actual results to differ materially from those expressed or implied by these forward-looking statements. These risks, uncertainties, and other factors include, among others, those risks and uncertainties described under the heading \"Risk Factors\" in Moderna's Annual Report on Form 10-K for the fiscal year ended December 31, 2025, filed with the U.S. Securities and Exchange Commission (SEC), and in subsequent filings made by Moderna with the SEC, which are available on the SEC's website at www.sec.gov. Except as required by law, Moderna disclaims any intention or responsibility for updating or revising any forward-looking statements contained in this press release in the event of new information, future developments or otherwise. These forward-looking statements are based on Moderna's current expectations and speak only as of the date of this press release.</p> <p>Moderna Contacts</p> <p>Media:<br>Chris Ridley<br>Vice President, Global Head of Communications<br>+1 617-800-3651<br>Chris.Ridley@modernatx.com</p> <p>Investors:<br>Lavina Talukdar<br>Senior Vice President &amp; Head of Investor Relations<br>+1 617-209-5834<br>Lavina.Talukdar@modernatx.com</p> <p>SOURCE: Moderna, Inc.</p> <p>View the original press release on ACCESS Newswire</p>",
      "category": "stocks",
      "image": null
    },
    {
      "id": "7be9881d91d83f423f1f9e59accb74bcebee489471f1c7a8812dcc3cd671ee9a",
      "title": "PTC to Announce Fiscal Q3'26 Results on Wednesday, July 29, 2026",
      "source": "Alpha Vantage - NEWS_SENTIMENT",
      "source_id": "alphavantage_news_sentiment",
      "published_at": "2026-07-08T10:59:55Z",
      "summary": "PTC (NASDAQ: PTC) is scheduled to release its fiscal 2026 third-quarter results on Wednesday, July 29, 2026, after the stock market closes. Senior management will host a live webcast and conference call at 5 p.m. ET on the same day to discuss the results. The earnings press re...",
      "content": "<h3>PTC to Announce Fiscal Q3'26 Results on Wednesday, July 29, 2026</h3> <p> </p> <p>What:</p> <p>PTC Fiscal Q3'26 Conference Call and Webcast</p> <p>When:</p> <p> Wednesday, July 29, 2026 </p> <p>Webcast:</p> <p>Register Here</p> <p>Replay:</p> <p>To access the replay via webcast, please visit this page.</p> <p>Please note that statements made on the conference call and webcast are as of the date of the conference call and webcast and PTC does not assume any obligation to update any statements made live or the archived call. Matters discussed may include forward-looking statements about PTC's anticipated financial results and growth, as well as about the development of products and markets, which are based on current plans and assumptions. Actual results in future periods may differ materially from current expectations due to a number of risks and uncertainties, including those described from time to time in reports filed by PTC with the U.S. Securities and Exchange Commission, including PTC's most recent reports on Form 10-K and 10-Q.</p> <p>About PTC</p> <p>PTC (NASDAQ: PTC) is a global software company enabling manufacturers and product companies to digitally transform how they design, manufacture, and service the physical products the world relies on. Headquartered in Boston, Massachusetts, PTC employs over 7,000 people and supports more than 30,000 customers globally. For more information, please visit www.ptc.com.</p> <p>Investor Contact</p> <p>Michael Maguire <br>mmaguire@ptc.com<br>investor@ptc.com </p> <p></p> <p>View original content to download multimedia:https://www.prnewswire.com/news-releases/ptc-to-announce-fiscal-q326-results-on-wednesday-july-29-2026-302815708.html</p> <p>SOURCE </p>",
      "category": "stocks",
      "image": null
    },
    {
      "id": "daa22f776d83aae52a2391aacf56759a9d24d9323a2c6625cddfc77250c4e96a",
      "title": "PTC sets July 29 webcast for fiscal Q3'26 results",
      "source": "Alpha Vantage - NEWS_SENTIMENT",
      "source_id": "alphavantage_news_sentiment",
      "published_at": "2026-07-08T10:59:55Z",
      "summary": "PTC (NASDAQ: PTC) announced it will release its fiscal 2026 third quarter results on Wednesday, July 29, 2026, after market close. Senior management will host a live webcast and conference call at 5:00 p.m. ET to discuss the results. The earnings release, presentation, and fin...",
      "content": "<h2>PTC to Announce Fiscal Q3'26 Results on Wednesday, July 29, 2026</h2> <h2>Rhea-AI Summary</h2> <p>PTC (NASDAQ: PTC) plans to release its fiscal 2026 third quarter results on Wednesday, July 29, 2026, after market close. Senior management will host a live webcast and conference call at 5:00 p.m. ET to review the results.</p> <p>The earnings release, presentation, and financial tables will be available beforehand in the Investor Relations section of PTC\u2019s website. The event may include forward-looking statements, and actual results may differ due to risks detailed in PTC\u2019s SEC filings.</p> <p>AI-generated analysis. How Rhea-AI works. Not financial advice.</p> <h3>Positive</h3> <ul> <li>None.</li> </ul> <h3>Negative</h3> <ul> <li>None.</li> </ul> <h3>Key Figures</h3> <h3>Previous Earnings date Reports</h3> Date Event Sentiment 24h Move Catalyst Apr 13 earnings date notice Neutral +0.6% Scheduled release of fiscal Q2 2026 results and related conference call. Jan 14 earnings date notice Neutral +0.2% Announcement of fiscal Q1 2026 results release timing and webcast details. <p>24h Move is the share-price change in the day after each event; other market factors may also have contributed.</p> <p>Recent earnings date announcements for PTC have been followed by modestly positive next\u2011day moves.</p> <h3>Historical Comparison</h3> <p>Across two prior earnings date announcements, PTC shares typically moved about 0.4% the next day, suggesting these scheduling releases have prompted only mild reactions and this notice carries similar informational content.</p> <p>The company has been issuing regular earnings date notices for fiscal Q1 and Q2 2026, and this fiscal Q3 2026 timing update continues that quarterly disclosure cadence.</p> <h3>Regulatory &amp; Risk Context</h3> <p>Short interest appears relatively low, indicating limited short-squeeze potential and suggesting that trading volatility is more likely to track fundamentals and news flow than positioning extremes.</p> <h3>Key Terms</h3> <h3>forward-looking statements regulatory</h3> <h3>u.s. securities and exchange commission regulatory</h3> <h3>form 10-k regulatory</h3> <h3>form 10-q regulatory</h3> <p>AI-generated analysis. How Rhea-AI works. Not financial advice.</p> <p>What:</p> <p>PTC Fiscal Q3'26 Conference Call and Webcast</p> <p>When:</p> <p>Wednesday, July 29, 2026 5:00 p.m. ET</p> <p>Webcast:</p> <p>Register Here</p> <p>Replay:</p> <p>To access the replay via webcast, please visit this page.</p> <p>Please note that statements made on the conference call and webcast are as of the date of the conference call and webcast and PTC does not assume any obligation to update any statements made live or the archived call. Matters discussed may include forward-looking statements about PTC's anticipated financial results and growth, as well as about the development of products and markets, which are based on current plans and assumptions. Actual results in future periods may differ materially from current expectations due to a number of risks and uncertainties, including those described from time to time in reports filed by PTC with the U.S. Securities and Exchange Commission, including PTC's most recent reports on Form 10-K and 10-Q.</p> <p>About PTC</p> <p>PTC (NASDAQ: PTC) is a global software company enabling manufacturers and product companies to digitally transform how they design, manufacture, and service the physical products the world relies on. Headquartered in Boston, Massachusetts, PTC employs over 7,000 people and supports more than 30,000 customers globally. For more information, please visit www.ptc.com.</p> <p>Investor Contact</p> <p>Michael Maguire <br>mmaguire@ptc.com <br>investor@ptc.com </p> <p></p> <p>View original content to download multimedia:https://www.prnewswire.com/news-releases/ptc-to-announce-fiscal-q326-results-on-wednesday-july-29-2026-302815708.html</p> <p>SOURCE PTC Inc.</p>",
      "category": "stocks",
      "image": null
    },
    {
      "id": "8750acaed0e17ffbb798143a966c670ef431c8b01a73d313e2ddc4d0978a74d3",
      "title": "Top Gainers &amp; Losers on 8 July: Aegis Logistics, HPCL, Bank of India, IndiGo, Coforge, MRF among top losers",
      "source": "LiveMint \u2014 Markets",
      "source_id": "livemint_markets",
      "published_at": "2026-07-08T10:58:34Z",
      "summary": "The Indian stock market faced heavy selling on Wednesday, with benchmark indices falling over 2% amid renewed U.S.-Iran tensions. The Nifty 50 dropped to 23,882, marking its biggest decline since March, and nearly all sectoral indices ended in the red, particularly the Nifty P...",
      "content": "<p>The Indian stock market witnessed heavy selling pressure on Wednesday, erasing part of its recent gains as tensions in the Middle East resurfaced after the U.S. and Iran resumed attacks. Market sentiment was further dented after U.S. President Donald Trump said the ceasefire agreement with Iran was \"over,\" triggering a sharp sell-off that dragged the benchmark indices down more than 2%.</p> <p>The Nifty 50 plunged 2.12% to settle below the 24,000 mark at 23,882, while the Sensex tumbled 2.14% to close at 76,503. This marked the biggest single-day decline for both benchmark indices since late March. The broader market also ended lower, with the Nifty Midcap 100 and Nifty Smallcap 100 falling 1.55% and 2.24%, respectively.</p> <p>All major sectoral indices ended in the red, with the Nifty PSU Bank index leading the losses after plunging 2.27%. It was followed by the Nifty Chemicals, Nifty Cement, Nifty Private Bank, Nifty FMCG, Nifty Media, Nifty Auto, and Nifty Oil &amp; Gas indices, all of which ended the session with losses of more than 2%.</p> <p>As per the media reports, the US launched strikes on Iran early Wednesday, hours after it revoked a license authorizing the sale of Iranian oil in retaliation for what it said were Tehran\u2019s attacks on ships in the Strait of Hormuz.</p> <p>In retaliation, Iran reportedly resumed attacks in the region, launching missiles at U.S. military sites in Bahrain and Kuwait. Both sides have accused each other of violating the ceasefire agreement.</p> <p>U.S. President Donald Trump later said the interim agreement with Iran was \"over\" but added that he would allow diplomatic talks to continue. His remarks raised concerns that the broader conflict in the Middle East could intensify again.</p> <p>More than 100 constituents of the Nifty 500 ended the session with losses of over 3%, with state-owned banks (sector) emerging as the worst performers. All PSU bank stocks closed in the red, led by Bank of India, Union Bank of India, Bank of Maharashtra, Canara Bank and Bank of Baroda, which declined by as much as 5.1%.</p> <p>Crude oil-sensitive stocks also witnessed sharp selling. InterGlobe Aviation fell 5% to \u20b95,124, while tyre makers MRF, JK Tyre &amp; Industries and Balkrishna Industries declined 4.1%, 4% and 3.9%, respectively.</p> <p>Among IT stocks, Mphasis and Coforge dropped 5.6% and 4.6%, respectively. Capital market-related stocks, including 360 One Wam, HDFC Asset Management, Motilal Oswal Financial Services, Nuvama Wealth Management, CDSL and CAMS, also witnessed another round of selling, falling between 3.5% and 5%.</p> <p>Meanwhile, all three state-run oil marketing companies (OMCs)\u2014Hindustan Petroleum Corporation (HPCL), Bharat Petroleum Corporation (BPCL) and Indian Oil Corporation (IOC)\u2014ended the session with losses of up to 5%.</p> <p>Despite the broad-based sell-off, a handful of stocks managed to buck the trend, led by Kalyan Jewellers India, which surged 5.5% to \u20b9374 apiece after analysts remained bullish on the stock following its June quarter business update.</p> <p>Ather Energy was another top performer in the Nifty 500 pack, rising 5.2% to \u20b91,200, while MCX also gained 4%.</p> <p>Other notable gainers included Chennai Petroleum, NALCO, Premier Energies, Acutaas Chemicals, Oil India, Info Edge (India), Exide Industries, RHI Magnesita India, BSE and Indus Towers, all of which ended the session with gains of more than 1.5%.</p> <p>Disclaimer: We advise investors to check with certified experts before making any investment decisions.</p> <p>Ksheera Sagar has been working as a Market Research Analyst at LiveMint for the past four years, covering stocks, commodities, and broader financial markets. In this role, he closely tracks daily market movements, corporate earnings, sector trends, and macroeconomic developments. &lt;br&gt;&lt;br&gt; He has over a decade of experience in the financial services industry and has previously worked with multiple organisations, including global investment bank J.P. Morgan, bringing strong research experience into the newsroom. &lt;br&gt;&lt;br&gt; During his career, he has gained extensive exposure to equity research, market analysis, and financial data interpretation, strengthening his expertise across asset classes and market cycles. &lt;br&gt;&lt;br&gt; He is known for his data-driven analysis and crisp, listicle-style market stories that break down complex financial developments across key markets for a wide audience. His strong research skills enable him to write detailed and insightful stories on stocks and sectors, focusing on the underlying factors driving market movements. &lt;br&gt;&lt;br&gt; His work combines quantitative insights with clear storytelling, presenting financial developments in a clear and structured manner. Moreover, he enjoys writing multibagger and listicle-style copies. Outside of work, Ksheera enjoys playing the piano and exploring new places. He has a keen interest in travel, music, and continuously learning about global markets and economic trends.</p> <p>Catch all the Business News , Market News , Breaking News Events and Latest News Updates on Live Mint. Download The Mint News App to get Daily Market Updates.</p>",
      "category": "stocks",
      "image": "https://www.livemint.com/lm-img/img/2026/07/08/1600x900/logo/2-0-1309458163-bse--1--0_1679981984752_1783506232006_1bc169da-eb96-4618-9e5d-1d191e09fdca.jpg"
    },
    {
      "id": "9507191bc92f6cb0f5ba64536e702a1de4a636c314fa15ef08d3495a859984e4",
      "title": "Campbell Soup steadies its business model as a staple food producer",
      "source": "Alpha Vantage - NEWS_SENTIMENT",
      "source_id": "alphavantage_news_sentiment",
      "published_at": "2026-07-08T10:58:00Z",
      "summary": "Campbell Soup Co. maintains its strong position in the packaged foods sector by focusing on its core soup and snack brands, emphasizing margin discipline, and investing in brand recognition. The company benefits from stable consumer demand for its products, which are less sens...",
      "content": "<p>Campbell Soup Co. (ISIN US1280301048) remains one of the best-known names in North American packaged foods, with roots that go back more than a century and a portfolio centered on soups and snacks sold through major grocery chains in the United States and Canada. The company has built its position by focusing on familiar brands and everyday consumption rather than cyclical or luxury demand. For investors, the long-term story is primarily about steady cash generation, competitive positioning in the food aisle, and disciplined capital allocation.</p> <h2>Stable demand for packaged foods</h2> <p>Campbell Soup Co. operates in a segment of the consumer staples market where demand tends to be relatively stable across economic cycles. Households buy shelf-stable soups, broths, sauces, and snack foods regularly, and these categories have historically been less sensitive to short-term economic volatility than discretionary goods. This gives the company a business profile that is oriented toward consistency and predictability rather than rapid swings in revenue.</p> <p>Much of the company\u2019s revenue comes from products that are consumed at home, whether as a quick meal solution or as an ingredient in everyday cooking. Supermarkets and mass retailers represent key sales channels, with the company competing for shelf space alongside other branded and private-label food producers. Over the years, Campbell Soup Co. has focused on maintaining brand recognition through packaging, advertising, and in-store promotions, aiming to keep its products visible and trusted among consumers.</p> <h2>Margin discipline and efficiency efforts</h2> <p>In the packaged food industry, margin management is a central strategic priority, and Campbell Soup Co. is no exception. The company\u2019s profitability depends on factors such as commodity costs for ingredients, energy, transportation, and packaging materials, as well as labor and marketing expenses. To support margins, management typically looks at pricing, product mix, and operational efficiency measures, including optimizing manufacturing footprints and logistics networks.</p> <p>Over time, the company has also considered portfolio moves, such as focusing more on core brands and divesting or reshaping less strategic lines, as a way to sharpen its margin profile. Within the soup category, for example, offerings range from condensed classics to ready-to-serve varieties, each with different price points and cost structures. In snacks, product formats and packaging sizes allow the company to participate in multiple price tiers while managing input costs. Analysts often evaluate how well these efforts translate into operating margin, free cash flow, and returns on invested capital.</p> <h2>Core brands and business model</h2> <p>Campbell Soup Co.\u2019s business model rests on owning and developing consumer brands that occupy prominent positions in the soup and snack categories. The flagship Campbell\u2019s soups are sold in canned form and are designed to be easy to store and prepare, making them a convenient option for quick meals or recipes. By maintaining a broad range of flavors and formats, from traditional chicken noodle and tomato soup to more contemporary variants, the company seeks to appeal to multiple consumer segments and taste preferences.</p> <p>Alongside soup, the company participates in the snack market with products such as crackers, chips, and related items that target everyday snacking occasions. This diversification within the broader food category helps balance seasonal and consumption patterns, as snacks and soups may see differing demand dynamics across the year. Marketing efforts typically highlight familiarity, comfort, and simplicity, positioning the company\u2019s brands as reliable choices for families and individuals looking for straightforward food solutions.</p> <h2>Campbell\u2019s canned soup as a representative product</h2> <p>A representative product for Campbell Soup Co. is the classic Campbell\u2019s canned soup, which exemplifies the company\u2019s approach to shelf-stable, branded food. These soups are distributed widely across grocery stores and mass retailers, and they are engineered to have long shelf lives, making them suitable for pantry stocking. The combination of recognizable red-and-white labeling, consistent flavor profiles, and easy preparation reflects the company\u2019s emphasis on convenience and brand continuity.</p> <p>From a business perspective, this product line showcases how Campbell Soup Co. manages scale in manufacturing, supply chains, and marketing. High production volumes support efficiency in sourcing ingredients and packaging, while broad distribution ensures that the brand remains visible to consumers across regions. For investors, the performance of signature products like canned soup is a key indicator of the company\u2019s ability to maintain market share and pricing power in its core categories.</p> <h2>Campbell Soup Co. stock and investor view</h2> <p>Campbell Soup Co. is listed in the United States, where its shares trade on a major stock exchange and are followed as part of the broader consumer staples universe. The stock is commonly compared to other packaged food and beverage companies, with market participants looking at metrics such as dividend yield, earnings stability, and valuation multiples relative to peers. Because the company\u2019s products are everyday food items, the stock is often grouped with defensive holdings that may provide more stable performance across different economic environments.</p> <p>Recent coverage of Campbell Soup Co. has highlighted themes like cost management, product innovation, and brand investment, as the company balances traditional offerings with changing consumer preferences. While short-term price movements can reflect broader market sentiment or sector rotation, the longer-term narrative tends to focus on how effectively the company maintains its competitive position on supermarket shelves and sustains its financial profile through disciplined operations and strategic choices.</p> <p>This article was generated automatically and technically reviewed before publication. Market prices, analyst data and company information are provided without warranty and may change at short notice. This content is for informational purposes only and is not investment, financial, legal or tax advice. It is not a recommendation to buy or sell any security. Investing in securities involves risk, including the possible loss of principal.</p> <p>Disclaimer zu unseren Artikeln: Keine Anlageberatung, keine Kauf oder Verkaufsempfehlung. Angaben zu Kursen, Unternehmen und M\u00e4rkten ohne Gew\u00e4hr; \u00c4nderungen jederzeit m\u00f6glich. B\u00f6rsengesch\u00e4fte k\u00f6nnen zu hohen Verlusten f\u00fchren. Unsere Beitr\u00e4ge werden ganz oder teilweise automatisiert mit Unterst\u00fctzung von AI erstellt und gepr\u00fcft.</p>",
      "category": "stocks",
      "image": null
    },
    {
      "id": "5de19dd6ac0960732d4a40f578e986722ee69de589c0d7fb5e43a049fafe30c1",
      "title": "News Corp Class B shares and the evolving media landscape",
      "source": "Alpha Vantage - NEWS_SENTIMENT",
      "source_id": "alphavantage_news_sentiment",
      "published_at": "2026-07-08T10:57:43Z",
      "summary": "News Corp (NWS) Class B shares are positioned at the intersection of traditional publishing, real-time news, and digital real estate, providing investors with diversified exposure to the global media and information economy. The company's strategy involves shifting towards dig...",
      "content": "<p>News Corp (NWS) Class B shares are positioned at the intersection of traditional publishing, real-time news, and digital real estate, providing investors with diversified exposure to the global media and information economy. The company&#x27;s strategy involves shifting towards digital formats and subscription models, alongside managing a portfolio that balances mature media assets with growth-oriented digital properties. This approach aims to stabilize earnings amidst industry changes, while its diverse revenue streams from advertising, subscriptions, and transactions are influenced by economic cycles and market-specific dynamics.</p>",
      "category": "stocks",
      "image": null
    }
  ]
}
