{
  "key": "us_news",
  "label": "US News",
  "generated_at": "2026-06-25T14:18:31Z",
  "articles": [
    {
      "id": "98a40ca61c7cbf7be0063d2d7a951e0702d71513e534a9e62da97af0de749cbf",
      "title": "Rebound in tech shares pushes Asian shares higher, while oil prices fall",
      "source": "ABC News \u2014 US Headlines",
      "source_id": "abc_us",
      "published_at": "2026-06-25T05:02:16Z",
      "summary": "Shares are mostly higher in Asia, led by tech-driven gains in Japan and South Korea",
      "content": "<h2>Rebound in tech shares pushes Asian shares higher, while oil prices fall</h2> <p>Shares are mostly higher in Asia, led by tech-driven gains in Japan and South Korea</p> <p>BANGKOK -- Shares were mostly higher Thursday in Asia, led by tech-driven gains in Japan and South Korea as major computer chipmakers\u2019 stocks surged following upbeat earnings reports from U.S. giants like Qualcomm and Micron Technology.</p> <p>Oil prices fell more than $1, bringing them closer to where they were before the war with Iran started.</p> <p>Qualcomm\u2019s share price surged 12% in afterhours trading after the company announced it had raised its forecast for revenue this year to $40 billion from $22 billion. It also announced a new computer chip for data centers called Dragonfly C1000 CPU that Meta plans to use.</p> <p>Micron Technology's shares jumped nearly 16% in afterhours trading after it upgraded its forecast and exceeded analysts' estimates.</p> <p>In Asian trading, Tokyo's Nikkei 225 index surged 4.1% to 71,995.59 as traders snapped up shares in technology companies. Chipmaker Tokyo Electron's shares gained 7.1%, while chip testing equipment maker Advantest's shares soared 13.4%.</p> <p>South Korea's benchmark, the Kospi, hit a new record, surging 5.9% to 8,968.22. Samsung Electronics's shares gained 5.4% and SK Hynix leaped 11.6%.</p> <p>Elsewhere in Asia, gains were more modest.</p> <p>Taiwan's Taiex climbed 0.8% and the Sensex in India was up 0.6%.</p> <p>The Shanghai Composite index picked up 0.4% to 4,125.76, while Hong Kong's Hang Seng dropped 1.4% to 23,090.27.</p> <p>Australia's S&amp;P/ASX 200 shed 0.5% to 8,768.20.</p> <p>On Wednesday, stocks wavered to a mixed close on Wall Street as losses for several tech giants including Microsoft weighed on the market. The S&amp;P 500 fell 0.1% to 7,358.22. The Dow Jones Industrial Average, which is less weighted with tech stocks, rose 10.4% to 51,848.90.</p> <p>The tech-heavy Nasdaq composite fell 0.4%, to 25,476.64.</p> <p>Microsoft lost 2.3% and Oracle slumped 4.6%.</p> <p>Many large tech companies have been behind Wall Street\u2019s record-setting run throughout the year, but analysts have warned their valuations may have become stretched.</p> <p>Google\u2019s parent company Alphabet slipped 0.2%. The company is replacing Verizon in the Dow on Monday. Its inclusion in the S&amp;P 500 means more to investors, however, because 401(k) accounts are much more likely to include an S&amp;P 500 index fund than anything tied to the Dow.</p> <p>Alphabet will become the fifth Magnificent 7 tech company to join the Dow. The others are Apple, Amazon, Microsoft and Nvidia.</p> <p>Oil companies had some of the biggest losses as prices fell while the U.S. and Iran negotiate a possible end to their war. Exxon Mobil fell 2% and Chevron lost 2.6%. Brent crude, the international standard, fell 3.8% to $73.87 a barrel. It has been trading below $80 in recent days but is still above the roughly $70 per barrel it was trading at in late February before the war began.</p> <p>U.S. crude prices fell 3.9% to $70.34 a barrel.</p> <p>Early Thursday, Brent was down 1.3% at $72.90, while U.S. benchmark crude lost 1.4% to $69.37.</p> <p>Some of the bigger winners on Wall Street included homebuilders following approval of legislation beneficial to the industry. KB Home surged 16.7% and D.R. Horton jumped 6.7%.</p> <p>The Federal Reserve will get an update on inflation later Thursday, when its preferred measure for prices is released. Economists expect the Personal Consumption Expenditures price index, or PCE, to show that prices rose 4.1% in May. That would be the highest level in three years.</p> <p>The Fed is worried over inflation, which has been rising as tariffs raise costs for many goods. It worsened as the war pushed energy and shipping prices higher and that impact is expected to linger even as oil and gasoline prices fall.</p> <p>In other dealings early Thursday, the U.S. dollar fell to 161.75 Japanese yen from 161.79 yen. The euro rose to $1.1368 from $1.1359.</p> <p>___</p> <p>AP Business Writers Damian J. Troise and Matt Ott contributed to this report.</p>",
      "category": "us_news",
      "image": "https://s.abcnews.com/images/US/wirestory_119e56cb6b1fc041b46af9bb778bdf07_4x3_384.jpg"
    },
    {
      "id": "09851d3aa4dc4fd99408905de82b47aff8472b6a74c57d5c1fca9fad2b920a97",
      "title": "New Mexico governor calls for criminal probe of DEA allowing fentanyl shipments to hit streets",
      "source": "ABC News \u2014 US Headlines",
      "source_id": "abc_us",
      "published_at": "2026-06-25T03:35:35Z",
      "summary": "New Mexico Governor Michelle Lujan Grisham is calling for a criminal investigation into whether federal authorities broke state law by allowing fentanyl pills to reach the streets",
      "content": "<h2>New Mexico governor calls for criminal probe of DEA allowing fentanyl shipments to hit streets</h2> <p>New Mexico Governor Michelle Lujan Grisham is calling for a criminal investigation into whether federal authorities broke state law by allowing fentanyl pills to reach the streets</p> <p>New Mexico\u2019s governor on Wednesday called for a criminal investigation into the Drug Enforcement Administration after an Associated Press investigation found federal agents allowed hundreds of thousands of fentanyl pills to reach the streets over a two-year period while pursuing larger drug-trafficking cases.</p> <p>Gov. Michelle Lujan Grisham asked the state\u2019s attorney general to examine whether the agency\u2019s actions violated New Mexico law, an extraordinary challenge to a federal law enforcement agency at a time when fentanyl remains one of the country\u2019s deadliest public health threats.</p> <p>The request follows an AP investigation that found DEA agents repeatedly allowed major fentanyl shipments to continue moving through New Mexico between 2023 and 2025 rather than seize them immediately, as agents sought to build cases against higher-ranking traffickers. The governor\u2019s call for a criminal review turns a debate over drug enforcement tactics into a question of whether federal agents themselves crossed legal lines while pursuing larger trafficking organizations.</p> <p>Current and former DEA agents told AP the strategy amounted to a gamble with public safety in a state ravaged by the fentanyl epidemic and may have violated U.S. Justice Department rules intended to safeguard the public from a drug the White House last year designated as a \u201c weapon of mass destruction.\u201d</p> <p>\u201cThere are no words to describe how reckless and dangerous these decisions were,\u201d Lujan Grisham said in a statement. \u201cMake no mistake: the DEA knew people would die if these pills made it into New Mexico communities, and the agency let it happen anyway.\u201d</p> <p>The DEA did not immediately respond to a request for comment on the governor\u2019s statement. The agency has contended it would not be plausible to seize every drug shipment and previously told AP in a statement \u201cthe investigative decisions at issue were lawful, reasonable under the circumstances and consistent with Department guidance.\u201d</p> <p>\u201cPublic descriptions suggesting that DEA knowingly permitted fentanyl to reach communities are false and fundamentally mischaracterize the facts,\u201d DEA spokesperson Amanda Wozniak wrote in an email.</p> <p>Alex Uballez, who served as U.S. attorney in New Mexico from May 2022 until February 2025, told AP that drugs went unseized at times due to his office\u2019s limited resources and his belief that prosecuting larger organizations has a bigger impact than intercepting every suspected drug transaction.</p> <p>It is not clear whether any fatal overdoses in the state can be directly attributed to the DEA strategy. While overdose deaths nationwide fell 14% last year, government data show New Mexico tallied a 21% spike.</p> <p>\u201cNew Mexican lives are not the federal government\u2019s cost of doing business,\u201d the governor wrote in her statement. \u201cI plan to hold the federal government accountable for this disaster and will explore every possible avenue of action against the federal government to right these wrongs.\u201d</p> <p>The AP investigation cited three current and former agents and government records, including an internal report of a 2023 delivery of 74,000 pills the DEA surveilled \u2014 but did not seize \u2014 at a mobile home park in Albuquerque.</p> <p>DEA whistleblower David Howell, who filed a complaint drawing attention to the unseized fentanyl, spoke Wednesday with congressional staffers. Empower Oversight, a whistleblower advocacy group representing Howell, has asked the Senate Judiciary Committee and Justice Department\u2019s Office of Inspector General to investigate the agent's allegations.</p> <p>Sen. Bernie Moreno, a Ohio Republican, called Howell's revelations \u201ca scandal of the highest order\u201d and said in a post on X he plans to find out how many American lives were lost due to the DEA's inaction.</p> <p>Meanwhile, victims groups also spoke out about DEA's inaction, saying its approach in New Mexico contradicts the agency's prominent \u201cOne Pill Can Kill\u201d campaign that warns as little as a few milligrams of fentanyl can cause a fatal overdose.</p> <p>\u201cKnowing the Justice Department had guidelines to seize the opioids whenever practical \u2014 and the fact these were ignored \u2014 is truly heartbreaking,\u201d said Michael Glownia, who lost his daughter to fentanyl in 2023 and founded a nonprofit organization to support families suffering similar losses.</p> <p>__</p> <p>Mustian reported from Miami.</p>",
      "category": "us_news",
      "image": "https://s.abcnews.com/images/US/wirestory_cb997b0097bba3ee9d5a98272ae65401_4x3_384.jpg"
    },
    {
      "id": "9153347f671af07e51694c3d6415c9f6b1f76ab7e28487d928e83bada0ecb0b3",
      "title": "New York City Council candidate is accused of forgery over AI-generated posts",
      "source": "ABC News \u2014 US Headlines",
      "source_id": "abc_us",
      "published_at": "2026-06-25T02:59:52Z",
      "summary": "A former New York City Council candidate has been charged with forgery over allegations he used artificial intelligence to post fake endorsements and news articles on social media",
      "content": "<h2>New York City Council candidate is accused of forgery over AI-generated posts</h2> <p>A former New York City Council candidate has been charged with forgery over allegations he used artificial intelligence to post fake endorsements and news articles on social media</p> <p>A former New York City Council candidate has been charged with forgery over allegations he used artificial intelligence to post fake endorsements and news articles on social media.</p> <p>Jonathan Rinaldi was arrested outside his home Wednesday and could face up to two years in prison if convicted. The 47-year-old ran unsuccessfully as a Republican for a council seat from Queens last year.</p> <p>The First Amendment to the U.S. Constitution does not generally protect fraudulent statements, but in a phone interview with The Associated Press on Wednesday, Rinaldi called it a matter of free-speech. He said he would not confirm or deny that he made the posts or generated the images at issue.</p> <p>\u201cI got arrested for social media posts,\u201d Rinaldi said. \u201cThis is an issue that strikes at the heart of our First Amendment freedoms \u2014 not just for me, but for everybody.\u201d</p> <p>Among the false posts he's accused of having made \u2014 primarily on Facebook and Instagram \u2014 was one claiming an endorsement from the Queens Jewish Alliance. Prosecutors say the post used the authentic logo of the organization as well as a legitimate-looking endorsement sheet.</p> <p>The complaint says the head of the Queens Jewish Alliance confronted him in a recorded phone call, and Rinaldi responded, \u201cWhen you are trying to fight against the establishment, I have to use every available tool that\u2019s at my disposal.\"</p> <p>In another post, Rinaldi fabricated a New York Post story claiming that then-Council Member Robert Holden, a Democrat, had crossed the aisle to endorse him, the Queens district attorney said.</p> <p>According to the charges, the fake story was accompanied by a doctored photo that appeared to show Holden shaking his hand \u2014 an image that Rinaldi prompted an AI platform to generate: \u201cface swap the man on the left.\u201d</p> <p>\u201cjust change the face the head is ok they are both bald just change the face,\u201d the prompt read, according to the charges.</p> <p>\u201cIn today\u2019s world it is important to hold people accountable for materially misrepresenting facts,\u201d District Attorney Melinda Katz said in a news release. \u201cAs alleged, the defendant used AI to replace factual political support and launched fabricated attacks against his opponent as fact in a deliberate effort to mislead voters ahead of a City Council election.\u201d</p> <p>The rapid spread of AI has posed myriad problems for lawmakers, as they try to get a handle on increasingly realistic \u2014 but fake \u2014 images, from deepfake pornography to other types of fraud. Over half of states have regulated the use of AI in elections to protect voters from being misled; many require disclosure, and some have also adopted criminal penalties. Some have exemptions for clear satire.</p> <p>A New York law adopted in 2024 requires disclosures of deepfakes in campaign materials and allows candidates who are targeted by them to go to court to block their dissemination.</p> <p>Still, the accessible technology has punctuated U.S. races this year. In a GOP U.S. House primary in Kentucky, for example, an AI-created ad depicted Republican U.S. Rep. Thomas Massie going on a romantic date and then to a hotel room with progressive U.S. Reps. Alexandria Ocasio-Cortez and Ilhan Omar.</p> <p>The laws Rinaldi is accused of violating \u2014 third-degree forgery and possession of forged instruments \u2014 predate AI. Under New York law, a person commits third-degree forgery when they falsely make, complete or alter \u201ca written instrument\u201d with the intent to defraud, deceive or injure another. A \u201cwritten instrument\u201d is defined in part as written or printed matter, including online writings, conveying information \u201ccapable of being used to the advantage or disadvantage of some person.\u201d</p> <p>The district attorney's complaint alleges myriad instances of Rinaldi using AI to generate doctored photos, including some of his Democratic opponent, Lynn Schulman, appearing to wear a shirt that read \u201cHot Girls for Zohran.\u201d The language of the prompt cited in the complaint suggests the reference to the city's Muslim mayor, Zohran Mamdani, was intended to hurt her support in the largely Jewish neighborhood of Forest Hills, where they were campaigning.</p> <p>The district attorney said Rinaldi further posted AI-generated videos appearing to show endorsements from a police precinct and an elementary school \u2014 public institutions which do not allow political endorsements.</p> <p>Rinaldi also was on the ballot in Tuesday\u2019s Democratic primary for state Assembly, where he was trounced by incumbent Andrew Hevesi. During the campaign Hevesi accused Rinaldi of fraudulently submitting documents to change his party registration, rendering him ineligible for the primary.</p> <p>Hevesi subsequently changed his party registration back. Rinaldi told The New York Times he denied having submitted the paperwork.</p>",
      "category": "us_news",
      "image": "https://s.abcnews.com/images/US/wirestory_995585d736361c976611f8846db171a2_4x3_384.jpg"
    },
    {
      "id": "f3bed9fcdbbbc4e434262b4473a041a76a72a3416ac3d61c330d636512562794",
      "title": "Indiana man charged after being accused of stalking WNBA player Sophie Cunningham",
      "source": "ABC News \u2014 US Headlines",
      "source_id": "abc_us",
      "published_at": "2026-06-25T00:51:55Z",
      "summary": "An Indiana man has been charged on accusations he stalked WNBA player Sophie Cunningham and sent her threatening and explicit messages on social media",
      "content": "<h2>Indiana man charged after being accused of stalking WNBA player Sophie Cunningham</h2> <p>An Indiana man has been charged on accusations he stalked WNBA player Sophie Cunningham and sent her threatening and explicit messages on social media</p> <p>An Indiana man was charged Wednesday on accusations he stalked WNBA player Sophie Cunningham and sent her threatening and explicit messages on social media.</p> <p>Kevin Singh, 48, faces felony charges for stalking and intimidation, as well as a misdemeanor harassment charge. He was arrested Tuesday, according to the Marion County Prosecutor\u2019s Office.</p> <p>Cunningham, a player with the Indiana Fever, told investigators she had been staying at home more and having nightmares because of Singh\u2019s continued messages, according to the affidavit. She was first made aware of Singh\u2019s alleged online conduct in February, she said.</p> <p>Singh's online behavior escalated that month and his conduct \u201cbecame increasingly threatening after he was contacted by team security,\" the Marion County Prosecutor\u2019s Office said in a news release.</p> <p>According to an affidavit, Singh allegedly sent numerous messages \u2014 including explicit messages \u2014 on the social media platform X in April. One of the messages featured the text, \u201cYou're literally down the street from me!\u201d After Cunnigham's team sent Singh a cease-and-desist letter on April 30, Singh sent more messages on X, making explicit and threatening comments, according to the affidavit.</p> <p>In September 2025, Singh hand-delivered a package addressed to \u201cSophie\u201d at Gainbridge Fieldhouse, Indiana Fever\u2019s home arena, containing a letter and a Guns N' Roses T-shirt sprayed with men's cologne, according the affidavit.</p> <p>\u201cThe internet has made it easier than ever to target, harass and intimidate others. Threats of violence, whether face-to-face or behind a keyboard, will be taken seriously,\u201d Marion County Prosecutor Ryan Mears said in a statement. \u201cComing forward is never easy, regardless of a person\u2019s position or public profile. The victim is setting an example by speaking out.\"</p> <p>A phone call to a number listed for Singh wasn't answered. It wasn't clear if he had an attorney yet.</p> <p>Singh is currently on probation in Hendricks County, Indiana, after he pleaded guilty in July 2025 to two felony counts of invasion of privacy, the Marion County Prosecutor's Office said.</p> <p>The incident comes after Cunningham's teammate, WNBA star Caitlin Clark, was the victim of stalking and harassing by a different man from Texas who was sentenced last year to 2 1/2 years in prison.</p>",
      "category": "us_news",
      "image": "https://s.abcnews.com/images/US/wirestory_08d7fe9943395a43f2e08aa317436602_4x3_384.jpg"
    },
    {
      "id": "514168d426d189f1aa1e52cd13b881b8da3c8ed26023d0837336647f8ef2defc",
      "title": "Trump's luncheon with GOP senators devolves into shouting match",
      "source": "CBS News \u2014 US",
      "source_id": "cbs_us",
      "published_at": "2026-06-24T23:33:07Z",
      "summary": "President Trump threw Capitol Hill into turmoil on Wednesday, abruptly canceling plans to sign a bill aimed at lowering housing costs. His closed-door luncheon with Republican senators turned into a shouting match over the war in Iran. The president wants senators to pass a di...",
      "content": "<p>Trump's luncheon with GOP senators devolves into shouting match</p> <p>President Trump threw Capitol Hill into turmoil on Wednesday, abruptly canceling plans to sign a bill aimed at lowering housing costs. His closed-door luncheon with Republican senators turned into a shouting match over the war in Iran. The president wants senators to pass a different bill that would change voting rules. Caitlin Huey Burns reports.</p>",
      "category": "us_news",
      "image": null
    },
    {
      "id": "5478201caa95269aa0f38c9fc34c13cd4244fcfb57e145d0bb5aff54a8c51d8a",
      "title": "Dozens of states could face new costs because of high error rates in SNAP food aid",
      "source": "ABC News \u2014 US Headlines",
      "source_id": "abc_us",
      "published_at": "2026-06-24T22:48:46Z",
      "summary": "Several dozen states might need to pay millions for food aid if they don't reduce errors in the Supplemental Nutrition Assistance Program",
      "content": "<h2>Dozens of states could face new costs because of high error rates in SNAP food aid</h2> <p>Several dozen states might need to pay millions for food aid if they don't reduce errors in the Supplemental Nutrition Assistance Program</p> <p>Several dozen states could have to fork over millions of dollars to provide food aid to lower-income residents, if they don\u2019t cut down on payment errors in the Supplemental Nutrition Assistance Program.</p> <p>Nine states, meanwhile, won\u2019t have to pay a penny toward SNAP benefits, because their error rates are so low that they won an exemption from a cost-sharing requirement included in a big tax-and-spending law signed by President Donald Trump.</p> <p>Data released Wednesday by the U.S. Department of Agriculture provides a first look at the winners \u2014 and potential losers \u2014 under the new law.</p> <p>The error rate refers rather the percentage of SNAP benefits paid either above or below what people should have received, primarily because of mistakes. While low-error states are guaranteed to owe nothing when the annual cost-sharing requirement begins in October 2027, others will have another year to try to reduce their errors and decrease the hit to their budgets.</p> <p>States with high error rates will have to make choices that could impact their residents. To fund SNAP benefits, do they spend less on public schools, law enforcement or mental health care? To save money, do they squeeze people off SNAP by making it harder to stay in the program? Or do they drop out entirely from the federal food aid program that\u2019s been around for decades?</p> <p>\u201cThere are billions of dollars that are at stake that states will have to find the money to be able to pay if they want to continue to operate a SNAP program,\u201d said Chloe Green, assistant director for policy at the American Public Human Services Association.</p> <p>The Supplemental Nutrition Assistance Program, known informally as food stamps, provides monthly payments to help low-income residents to buy food. More than 37 million people nationwide received SNAP benefits in March, according to preliminary USDA figures. That's down nearly 5 million people \u2014 over 11% \u2014 from a year earlier.</p> <p>A law signed by Trump last July expanded requirements for many adult SNAP recipients to work, volunteer or participate in job training. The new work and cost-share requirements are intended to increase accountability for participants and states \u2014 and to provide federal savings that offset new tax cuts.</p> <p>\u201cThese payment error rates are further proof that state accountability is severely lacking in SNAP,\u201d said Agriculture Secretary Brooke Rollins.</p> <p>Administrative costs for SNAP currently are split 50-50 between the federal government and states. But federal law requires states to start paying 75% of SNAP administrative costs this October.</p> <p>The federal government currently covers the full cost of SNAP benefits provided to people. But beginning in October 2027, states with SNAP error rates of 6% or greater could have to pay a portion of the benefits.</p> <p>The error rates released Wednesday, which cover the 2025 fiscal year, are the first that matter. Federal law says states can choose to use either their 2025 or 2026 error rates when determining what percentage of SNAP benefits they must pay starting in October 2027.</p> <p>South Dakota had the lowest error rate last year at about 2.5%. Nebraska had an error rate of 5.9% \u2014 just barely below the cutoff to avoid paying part of the SNAP benefits. Other states with error rates below 6% were Idaho, Iowa, Kentucky, Vermont, Utah, Wisconsin and Wyoming.</p> <p>Federal law sets a sliding scale for how much money states must pay toward SNAP benefits. States with error rates between 6%-8% will have to eventually pay 5% of the benefit costs. Those with error rates between 8%-10% will have to pay 10% of benefit costs. And those with error rates over 10% will have to pay 15% of benefit costs.</p> <p>Consider Missouri as an example. It had an error rate of 8.7% last year. Unless it improves next year, the state will have pick up 10% of SNAP benefit costs starting in October 2027.</p> <p>Missouri residents received about $1.5 billion of SNAP benefits in 2024, the latest year for which federal data is available. If that same amount of benefits is paid in the future, Missouri could have to cover $150 million of the costs; that's a sum greater than the total budgeted for several state prisons.</p> <p>An exception in the federal law gives states with the highest error rates more time to try to reduce them. States with error rates of at least 13.34% last year will receive a delay in their cost-share requirements until at least the 2029 fiscal year.</p> <p>The delay will benefit Alaska, which had the highest error rate of over 23%. Other jurisdictions receiving a one-year, cost-share delay are Delaware, Georgia, Illinois, New Mexico, Oregon and the District of Columbia.</p> <p>More states still have a shot at getting an extension. States whose error rates exceed 13.34% in 2026 could have their cost-sharing requirements delayed until the 2030 fiscal year.</p> <p>A recent survey of state agencies that run SNAP found that most already are analyzing the root causes of their payment errors. The mistakes appear to be evenly attributable to SNAP recipients and program administrators, and many states are planning to increase staff focused on eliminating errors, according to the survey released by American Public Human Services Association.</p> <p>But states also are planning for cuts, if they are forced to pay a portion of SNAP benefits. More than a quarter of the states responding to the survey said they could consider narrowing eligibility policies, and four states said they could consider withdrawing from SNAP entirely. The report did not list those states.</p> <p>Some advocates for low-income residents want Congress to postpone the SNAP cost-share requirements for all states. That would require a change in federal law.</p> <p>The error-rate data \u201creally underscore the urgent need for Congress to delay this massive cost shift to state budgets,\u201d said Katie Bergh, senior policy analyst at the left-leaning Center on Budget and Policy Priorities.</p> <p>Many people already are struggling with high grocery prices, and \u201cthis is coming at a time when millions of people have already lost food assistance,\u201d Bergh said.</p>",
      "category": "us_news",
      "image": "https://s.abcnews.com/images/US/wirestory_4fa06549e3ec2bd1a1c665b1985cefea_4x3_384.jpg"
    },
    {
      "id": "443bbd4c05f99ea2b399d3db75f29e3d8ff17b4da417485e0567d839068df608",
      "title": "South Dakota incumbent Republican lawmaker facing felony election fraud counts",
      "source": "ABC News \u2014 US Headlines",
      "source_id": "abc_us",
      "published_at": "2026-06-24T22:30:08Z",
      "summary": "An incumbent South Dakota Republican state senator is facing two felony counts after an investigation found falsified signatures on forms he tried to submit for state GOP positions",
      "content": "<h2>South Dakota incumbent Republican lawmaker facing felony election fraud counts</h2> <p>An incumbent South Dakota Republican state senator is facing two felony counts after an investigation found falsified signatures on forms he tried to submit for state GOP positions</p> <p>SIOUX FALLS, S.D. -- An incumbent South Dakota legislative leader is facing two felony counts, accused of falsifying signatures to put candidates forward for state Republican Party positions without them knowing.</p> <p>Republican state Sen. Thomas Pischke of Dell Rapids represents a deep red district outside Sioux Falls and is seeking a third term in November. He faces two felony counts of knowingly submitting a falsified or forged document.</p> <p>Pischke turned himself in to the Minnehaha County Jail on Tuesday and was released on a promise to appear for all future court dates, the sheriff's office said. An initial hearing is set for July 7.</p> <p>Pischke has agreed to step away from his duties in the party, including serving on the executive board of the Minnehaha County Republicans, as the case plays out, said Jim Eschenbaum, chair of the South Dakota Republican Party.</p> <p>\u201cIt\u2019s a bad optic for the party,\u201d Eschenbaum said Wednesday. \u201cI\u2019m disappointed that this has happened. But we also have to just be honest about what\u2019s going on, you know, and deal with it.\u201d</p> <p>The Associated Press left email messages this week for Pischke and his attorney seeking comment.</p> <p>If convicted of a felony, Pischke would not be able to hold a position with the state Republican Party, Eschenbaum said. It is unclear whether Pischke would be able to serve in the Legislature. State law says any person convicted of perjury, bribery or an infamous crime may not serve in the Legislature.</p> <p>The Associated Press left phone messages Wednesday with the Legislative Research Council and state Senate President Pro Tempore Chris Karr seeking clarification.</p> <p>Jessica Meyers, vice chair of the South Dakota Democratic Party, said any official who interferes with a public process should be held accountable.</p> <p>\u201cWe believe in free and fair elections at every level of the political process,\" she said.</p> <p>The biennial Republican Party state convention begins Thursday, but Pischke will not be there. At the convention, precinct committee people serve as delegates and voting members to determine party leadership and help set the party's agenda. Outside the convention, committee people perform duties in their communities like contacting and registering voters.</p> <p>The charges against Pischke came after a monthslong investigation into the filings. The county auditor's office had identified 16 forms for precinct committee positions with suspected fraudulent signatures and discrepancies with registered voting addresses.</p> <p>The auditor\u2019s office called the nominees on the suspected fraudulent forms, and the majority said they didn\u2019t fill them out. None were put on the ballot during the June Republican primary, according to Eschenbaum.</p> <p>Pischke admitted to filling out his own form at the auditor's office to run for precinct committeeman but he denied filling out forms for others, the affidavit stated. He won the position in June, according to the auditor's office.</p> <p>The investigation uncovered DNA evidence matching Pischke on envelopes containing the forms and used surveillance video to identify a vehicle near a mail drop box that was registered to Pischke.</p> <p>Pischke ran unopposed in GOP Senate primary. He is facing Bryan Breitling, a former Republican state lawmaker who is running as an independent, in the November general election.</p> <p>Breitling said Tuesday that he entered the race because the district needs a senator with integrity.</p> <p>\u201cThese charges are the latest on a long list of poor judgments made by the senator,\u201d he said.</p>",
      "category": "us_news",
      "image": "https://s.abcnews.com/images/US/wirestory_e46bd4d3485043d968a95940170bd6d6_4x3_384.jpg"
    },
    {
      "id": "6b7fe942c33a9232c978ebfbe43df5c24647ba47c5f91ab483b6fccd00f4793b",
      "title": "Trump refuses to sign bipartisan housing bill into law. What does that mean for homebuyers, renters?",
      "source": "ABC News \u2014 US Headlines",
      "source_id": "abc_us",
      "published_at": "2026-06-24T22:30:07Z",
      "summary": "A sprawling legislative package aimed at lowering the cost of housing and spurring more home construction won broad bipartisan approval from Congress this week, but it\u2019s hit a major roadblock in becoming law",
      "content": "<h2>Trump refuses to sign bipartisan housing bill into law. What does that mean for homebuyers, renters?</h2> <p>A sprawling legislative package aimed at lowering the cost of housing and spurring more home construction won broad bipartisan approval from Congress this week, but it\u2019s hit a major roadblock in becoming law</p> <p>LOS ANGELES -- A sprawling legislative package aimed at lowering the cost of housing and spurring more home construction won bipartisan approval from Congress this week, but it's hit a major roadblock in becoming law: President Donald Trump.</p> <p>The White House supported the 21st Century ROAD to Housing Act, but on Wednesday Trump canceled the signing ceremony for the bill, saying he would not sign the measure until Congress passes legislation that would require proof of citizenship for all voters.</p> <p>Here\u2019s what to know.</p> <p>The measure is the culmination of months of negotiations by lawmakers who combined dozens of bills meant to address how housing affordability for both renters and aspiring homeowners in the U.S. has grown increasingly out of reach for many Americans.</p> <p>The bill would reduce federal regulations, streamline environmental reviews, speed up the construction process and curb the influence of corporate landlords by limiting their ability to purchase single-family homes.</p> <p>Still, it's not a silver bullet for all the factors that contribute to reduced housing affordability, including lack of construction labor, rising insurance costs and years of subdued wage growth relative to sharply rising rents and home prices.</p> <p>Even so, the bill has drawn broad support from the real estate industry, including organizations representing homebuilders and apartment complex owners, as well as housing advocates.</p> <p>\u201cWe need more homes built, and legislation that removes construction barriers is exactly what the market needs right now,\u201d said Daryl Fairweather, chief economist at Redfin. \"Homebuyers who were hoping for relief may have to wait even longer, and in a market already starved for inventory, that\u2019s a tough pill to swallow.\u201d</p> <p>Housing has grown into a hot-button issue among voters in recent years as homeownership and rents in many areas have become less affordable for many Americans.</p> <p>The U.S. housing market has been in a slump since 2022, when mortgage rates began to climb from pandemic-era lows. Sales of previously occupied U.S. homes were essentially flat last year, stuck at a 30-year low. While sales accelerated in May to their fastest pace since December, they continue to hover close to a 4 million annual pace, far short of the historic norm that is closer to 5.2 million, limited partly by elevated mortgage rates.</p> <p>Years of soaring home prices, especially in the early part of this decade when rock-bottom mortgage rates fueled a buying frenzy, have left many would-be homebuyers frozen out of the market. And a chronic shortage of homes for sale nationally, due partly to years of below-average new home construction, has helped prop up home prices even in a multiyear sales slump.</p> <p>Home prices have increased 54% nationwide since 2020, and last year the median existing single-family sales price was nearly five times the median household income, according to researchers at Harvard's Joint Center for Housing Studies.</p> <p>Renters, meanwhile, have seen little improvement in affordability. While the median U.S. monthly rent has been declining for nearly three years, it was still 17.2% higher in May than before the pandemic, according to data from Realtor.com.</p> <p>One of the biggest hurdles to homeownership has been an imbalance between supply and demand in many parts of the country.</p> <p>When there are fewer homes on the market, that helps prop up home prices even during a slowdown. Conversely, during times when mortgage rates are low, buyers end up competing for fewer homes, which drives up prices.</p> <p>The housing bill would help increase the supply of housing, particularly when it comes to smaller, more affordable starter homes.</p> <p>It amends existing regulations to boost construction of manufactured homes, which tend to be more affordable than other types of newly built homes, and expand access to government-backed loans to include construction of standalone dwellings a homeowner can rent out.</p> <p>The bill also provides new dollars for communities to turn abandoned infrastructure into housing, and provides guidelines for communities that want to reform outdated zoning regulations, which often limit larger housing developments.</p> <p>\u201cIt won\u2019t make housing more affordable overnight, but in the coming years we will see more construction of town homes, multifamily housing, and ADUs,\u201d notes Fairweather, saying the additional supply \"will relieve the pressure on home prices, and make it easier for homebuyers to break into the market.\u201d</p> <p>The legislation includes a broad set of provisions, including an expansion of government rental assistance and affordable housing construction programs , and measures aimed at encouraging state and local governments to make it easier to build new homes and apartments, including federal funding to places exceeding the median rate of homebuilding.</p> <p>In addition, the bill would raise limits on the number of public housing units that can receive financing for renovations and codify a recovery program to help expedite funds to communities rebuilding after disaster.</p> <p>It also requires new renter protections.</p> <p>\u201cFamilies are struggling under the heavy weight of housing costs that have climbed for decades,\u201d said San Diego Mayor Todd Gloria, who is president of the U.S. Conference of Mayors. \"There\u2019s no time to waste. Without federal action, America\u2019s housing shortfall will continue to grow, falling another 2 million units behind in the next five years.\u201d</p> <p>While hailed as a significant step, the federal government's power to dictate things like how many homes are built or rents is limited, given that most of the regulations on construction, such as zoning laws, and other facets of real estate are determined by local and state governments.</p> <p>So, even if the bill is delayed, it's not like it would have had an immediate impact on local house prices, for example. But it would set back the clock on new construction projects that might not otherwise get the go-ahead.</p> <p>\u201cThe sooner this bill becomes law, the sooner builders and homebuyers will benefit from its downstream effects,\u201d said Danielle Hale, chief economist at Realtor.com. \u201cEven if the president were to sign this bill immediately, many of the provisions will take time to impact builder planning and projects in the pipeline, so there is going to be a delay before consumers feel the impacts of this legislation either way.\u201d</p> <p>Trump's decision to not sign the legislation into law Wednesday could end up just temporarily delaying the measure from taking effect.</p> <p>The House passed the bill in a 358-32 vote on Tuesday and the Senate passed it 85-5 on Monday. That level of support is what's colloquially called a veto-proof majority.</p> <p>Still, if Trump were to veto the measure, the Senate and the House would have to vote again to override the veto.</p> <p>It may not come to that.</p> <p>Speaker Mike Johnson said Wednesday that he had spoken with Trump earlier in the day and was confident the president would sign the bill.</p> <p>\u201cThe president, when we go through the details of the bill, he\u2019s going to understand that it\u2019s a good product,\u201d Johnson said.</p>",
      "category": "us_news",
      "image": "https://s.abcnews.com/images/US/wirestory_85db7cc9fead2730dda9cfa7706f8189_4x3_384.jpg"
    },
    {
      "id": "3011408ea64b5174ba22f4ca09f7dde4c731b77f34386e9dba48c21ef32d9b52",
      "title": "Pentagon restores mandatory flu shots for all recruits as boot camp outbreak sickens nearly 300",
      "source": "ABC News \u2014 US Headlines",
      "source_id": "abc_us",
      "published_at": "2026-06-24T22:30:05Z",
      "summary": "The Pentagon says military boot camps are once again requiring flu vaccinations for all recruits",
      "content": "<h2>Pentagon restores mandatory flu shots for all recruits as boot camp outbreak sickens nearly 300</h2> <p>The Pentagon says military boot camps are once again requiring flu vaccinations for all recruits</p> <p>WASHINGTON -- The Pentagon said Wednesday that boot camps for all the military services are once again requiring the flu vaccination for all recruits after Defense Secretary Pete Hegseth made the shot optional for the military at the end of April.</p> <p>The development, confirmed to The Associated Press by a Pentagon official, comes amid a growing, weekslong, flu outbreak at the U.S. Air Force's boot camp at Lackland Air Force Base that has sickened nearly 300 people. However, the official, who spoke on condition of anonymity to discuss details not cleared for public release, maintained that the permission to mandate the vaccinations was unrelated to the outbreak.</p> <p>When Hegseth first announced the repeal of the flu vaccine mandate in April, citing \u201cmedical autonomy\u201d and religious freedom, he allowed the services to ask for exceptions \u2014 or permission to keep the vaccine mandatory \u2014 within 15 days of the rollout.</p> <p>The Pentagon official explained that the decision on those exceptions were being finalized earlier in June and the timing with the outbreak at Lackland was just a coincidence. Only 40% of the new trainees moving through the bootcamp at Lackland opted to receive the shot once it became optional, a source familiar with the situation told the Associated Press. The person spoke on the conditional of anonymity because the information was not cleared for public release.</p> <p>The base handles roughly 700 new recruits every week, according to Air Force figures, and the close quarters environment has long been recognized as being conducive to the spread of disease.</p> <p>Recruits are exposed to high stress, low sleep, and close contact conditions for weeks. They typically sleep together in large, open rooms, shower communally, and conduct much of their instruction and inspections in close contact.</p> <p>The Lackland outbreak, which is now roughly three weeks long, has produced 275 confirmed cases of the flu, Democratic Rep. Joaquin Castro said in a social media post. Castro's district includes part of the base on which the Air Force boot camp resides.</p> <p>The new outbreak is \u201cnot unusually concerning,\u201d said Dr. Arnold Monto, a flu expert and emeritus professor at the University of Michigan.</p> <p>Flu is mainly a problem in the late fall and winter \u2013 \u201cflu season,\u201d as it is known. But flu viruses routinely circulate at lower levels in warmer months, too.</p> <p>Concentrated flu outbreaks can occur in the spring and summer, but tend to be seen mainly on military bases, cruise ships and other settings where a lot of people are gathered together indoors, Monto said.</p> <p>If you want to prevent flu outbreaks, \u201cit is especially necessary to vaccinate when there are group settings,\u201d Monto said.</p> <p>In a statement to the media, Sean Parnell, the Pentagon\u2019s top spokesman, confirmed that exceptions were granted to the Army, Navy, and Air Force as well as the National Security Agency and the Defense Health Agency but wouldn\u2019t offer further details.</p> <p>However, both Army and Navy officials have said that they have also asked for permission to make the shot mandatory for certain broad groups that include troops deploying overseas, healthcare workers, and child care workers.</p> <p>Families Fighting Flu, an advocacy organization, cheered any change to increase vaccinations.</p> <p>\u201cFor decades, the military prioritized the health and safety of troops and the public by requiring flu vaccine for recruits. It\u2019s unfortunate that more than 200 individuals at Lackland Air Force Base in Texas became ill when that requirement was rescinded.\u201d said Michele Slafkosky, the organization\u2019s executive director, in a statement.</p> <p>\u201cThis updated guidance from the military will save lives,\u201d he added.</p>",
      "category": "us_news",
      "image": "https://s.abcnews.com/images/US/wirestory_4255f063ef99ea2d00cb24fec8793c32_4x3_384.jpg"
    },
    {
      "id": "daf9fada51b3aba95d389586217688ad21a42d1ecdfb9bb271833e84d6ea914c",
      "title": "Lawmakers demand answers as turmoil over Reflecting Pool repair continues",
      "source": "ABC News \u2014 US Headlines",
      "source_id": "abc_us",
      "published_at": "2026-06-24T22:30:03Z",
      "summary": "Congressional Democrats are calling for investigations into renovations at the Lincoln Memorial Reflecting Pool, as the ongoing drama over the president\u2019s problem-plagued, $16 million rehabilitation project continues to roil the capital",
      "content": "<h2>Lawmakers demand answers as turmoil over Reflecting Pool repair continues</h2> <p>Congressional Democrats are calling for investigations into renovations at the Lincoln Memorial Reflecting Pool, as the ongoing drama over the president\u2019s problem-plagued, $16 million rehabilitation project continues to roil the capital</p> <p>WASHINGTON -- Congressional Democrats called for investigations Wednesday into renovations at the Lincoln Memorial Reflecting Pool, as the ongoing drama over the president\u2019s problem-plagued, $16 million rehabilitation project continued to roil the capital.</p> <p>Lawmakers in the House and Senate demanded answers about the saga that's been highlighted in the news cycle for weeks, even as the White House has repeatedly blamed \u2014 without evidence \u2014 unidentified vandals for peeling paint and other problems. Six people have been arrested, President Donald Trump said, without providing details, and a local wildlife nonprofit conducted necropsies on dead ducks found near the Reflecting Pool. The president has said the pool may need to be drained once again for additional repairs.</p> <p>Connecticut Sen. Richard Blumenthal, the top Democrat on the Senate Permanent Subcommittee on Investigations, challenged the Trump administration over no-bid contracts for work on the Reflecting Pool, saying they were awarded to vendors with previous relationships to Trump.</p> <p>National Park Service projects undertaken at Trump\u2019s behest in the Washington area \u201chave been marked by blatant corruption, a shocking lack of transparency, disregard for legal requirements and apparent incompetence,\u201d Blumenthal wrote Wednesday in a letter to Interior Secretary Doug Burgum and Jessica Bowron, the acting Park Service director.</p> <p>\u201cRushed no-bid contracts given to unqualified vendors with previous relationships to the president resulted in a reflecting pool more covered with algae than before, with freshly painted chunks of paint peeling from the bottom to float on the pool\u2019s surface,\u201d Blumenthal said.</p> <p>The nation's capital \u201cwill now celebrate America's 250th birthday with an empty reflecting pool, a testament to incompetence and corruption,\u201d he added.</p> <p>Ohio-based Green Water Solutions was given a $1.7 million contract to install a water-purification system in the Reflecting Pool, while Virginia-based Atlantic Industrial Coatings was awarded $14.7 million to repaint and waterproof the pool\u2019s concrete floor.</p> <p>Both contractors have ties to Trump entities, said California Rep. Robert Garcia, the top Democrat on the Committee on Oversight and Government Reform.</p> <p>Trump pledged to beautify the century-old Reflecting Pool ahead of the nation's 250th birthday celebrations, draining its water and directing the bottom to be painted a color he dubbed \u201cAmerican flag blue.\u201d But since the site was restored, its water has been plagued by an algae bloom and pieces of the new coating have appeared to be peeling off the bottom.</p> <p>The White House and Interior Department did not respond to requests for comment on the Democrats' claims.</p> <p>Without evidence, Trump has repeatedly blamed the peeling paint on vandalism, including a \u201c350-foot gash\u201d in the liner, as the administration faces a self-imposed deadline to complete the renovation before July 4th. Trump also has said the federal government would release images to substantiate his claim. None were made public as of Wednesday.</p> <p>Trump said Wednesday that \u201csick people\u201d had used razors and box cutters to slice portions of the lining. He wasn\u2019t sure if the pool draining would come before or after the July 4 holiday, during which tens of thousands of people will be at the National Mall.</p> <p>\u201cDonald Trump\u2019s disastrous renovation of our national reflecting pool is his latest failed vanity project,\u201d Garcia said, calling the projects a waste of taxpayer money.</p> <p>The owner of Green Water Solutions, John Cafaro, is a Trump donor who lives near Mar-a-Lago, the president\u2019s private club in Florida.</p> <p>Atlantic Industrial Coatings is owned by Curtis \u201cEddie\u201d Wood. The company said this week it has identified some areas in the Reflecting Pool that require repairs, adding that the work will done once the pool is drained. It was unclear when that will happen.</p> <p>Amid the calls for investigations, Democratic Sen. John Hickenlooper of Colorado called for Trump to personally reimburse American taxpayers for the pool renovations, which he called \u201ca national embarrassment.\u201d</p> <p>Americans expect their tax dollars \u201cto fix roads, support schools and protect our public lands,\u201d Hickenlooper wrote in a letter to Trump. \u201cThey do not expect to bankroll failed presidential vanity projects. The bill for this fiasco should only belong to you, Mr. President.\u201d</p> <p>___</p> <p>Associated Press writer Meg Kinnard contributed to this story.</p>",
      "category": "us_news",
      "image": "https://s.abcnews.com/images/US/wirestory_161e64c70c55856ee082938b50bfa0bc_4x3_384.jpg"
    },
    {
      "id": "8a4bc6cd5f28a69bbbd1416ecacc46bde6b2a0b7adb3bf050dc1de183d9934b9",
      "title": "Trump's showdown with Republican Sen. Cassidy: Inside the blow-up on Capitol Hill",
      "source": "ABC News \u2014 US Headlines",
      "source_id": "abc_us",
      "published_at": "2026-06-24T22:30:00Z",
      "summary": "President Donald Trump's visit to Capitol Hill is rekindling a feud with one Republican senator",
      "content": "<h2>Trump's showdown with Republican Sen. Cassidy: Inside the blow-up on Capitol Hill</h2> <p>President Donald Trump's visit to Capitol Hill is rekindling a feud with one Republican senator</p> <p>WASHINGTON -- WASHINGTON (AP) \u2014 \u201cWould you really like to know?\u201d Sen. Bill Cassidy asked President Donald Trump.</p> <p>Just hours after refusing to sign a bipartisan housing bill that Republicans hoped would boost their election-year prospects, the president was attending a private lunch Wednesday with the Senate GOP. Trump wondered aloud how anyone could have voted for a war powers resolution a day earlier that seeks to block further U.S. military action against Iran.</p> <p>Cassidy, one of the four Republicans who backed the measure, was ready with an answer.</p> <p>\u201cI stood and said, \u2018You have not told the American people what's going on,'\u201d Cassidy, a Louisiana Republican, recounted to reporters afterward. \u201cThis is supposed to last four weeks. It's lasted four months. Our original objectives have not been achieved.\u201d</p> <p>Things deteriorated from there.</p> <p>When Cassidy told Trump he would continue voting for war powers resolutions until there's a congressional briefing on developments in Iran, the senator recalled that Trump \u201cdid not particularly care for my comments\u201d and \u201craised his voice.\u201d</p> <p>Trump repeatedly told Cassidy to sit down, according to a person familiar with the situation who spoke on condition of anonymity to describe a private meeting. At one point, the president called the senator a \u201clunatic,\" the person said.</p> <p>Cassidy acknowledged losing his temper, which he said was \u201cnot appropriate.\u201d</p> <p>\u201cBut I again matched his tone and volume,\" Cassidy said, before recalling that he eventually sat down. \u201cAnd so I sat down and tried to de-escalate. I guess my point is, though, that the American people need to know more than we're being told.\u201d</p> <p>The back-and-forth was a remarkable exchange between a two-term Republican senator and a president from his own party. It's a departure from the posture many congressional Republicans have adopted during Trump's second term as they mostly avoid criticizing him in public while expressing frustration in private.</p> <p>But the comments reflected the growing unease among congressional Republicans about the durability of their thin majorities on Capitol Hill in this year's elections, particularly in the turmoil of the Iran war. And it reflected the long-festering enmity between Trump and Cassidy that came to a head this year.</p> <p>Trump effectively ended Cassidy's political career by backing a Republican rival in Louisiana's Republican primary. Cassidy last month became the first incumbent senator in 14 years to lose a primary, driven largely by his vote to convict Trump in the impeachment trial for his role in the Jan. 6, 2021, attack on the U.S. Capitol.</p> <p>Cassidy said Trump brought up his election defeat as they argued. He described the president's comments as part of \u201cwhatever comes to mind as to demean another person.\u201d</p> <p>Before his losing the primary, Cassidy spent much of his time trying to make amends, largely supporting the president's policies and nominees. He has taken a tougher stance since losing his primary, freed from having to face Republican voters who remain loyal to Trump.</p> <p>\u201cIt does not appear, although I don\u2019t know for sure, that the course of (the Iran war) is going the way that we were told,\u201d Cassidy said. \u201cAnd so I make no apologies for standing up to the president, if you will, trying to demand that more information be shared with the Senate, and more information be shared with the American people.\u201d</p> <p>Cassidy's colleagues didn't offer robust support, with Trump in the room, though Cassidy said they didn't have much of a chance.</p> <p>\u201cThe president just kind of talked and talked and talked and talked and talked,\u201d Cassidy said.</p> <p>The White House didn\u2019t respond to a request for comment on Cassidy\u2019s characterization of the meeting and some Republicans tried to play down the clash.</p> <p>\u201cY'all act like no one ever yelled at each other,\u201d Sen. Roger Marshall, R-Kansas, told reporters.</p> <p>Sen. Tommy Tuberville, an Alabama Republican and former college football coach, described the encounter as \u201chalftime talk\u201d in the aftermath of the senator's defeat.</p> <p>\u201cProbably needed to be said, end of the day,\u201d he said. \u201cI think they got a lot of \u2014 both of them \u2014 got a lot off their chests.\u201d</p> <p>Others noted dryly that the meeting had been advertised as a chance for Trump and the Republicans to get on the same page.</p> <p>\u201cThat was quite a unity message,\u201d said Sen. John Cornyn, the Texas Republican who lost his primary to a Trump-backed challenger just weeks after Cassidy.</p> <p>Asked if he was being sarcastic, Cornyn stepped into an elevator and let the doors close.</p> <p>___</p> <p>Associated Press writer Lisa Mascaro in Washington contributed to this report.</p>",
      "category": "us_news",
      "image": "https://s.abcnews.com/images/US/wirestory_703c5fa45438ecae75d53062eea3aa87_4x3_384.jpg"
    },
    {
      "id": "c36c2c0fe5b7486ca3ee149b3266a28e0b5ca0f3ef1848848fb0f7d03e4df6d1",
      "title": "What to know about the push to make Bible stories required reading in Texas public schools",
      "source": "ABC News \u2014 US Headlines",
      "source_id": "abc_us",
      "published_at": "2026-06-24T21:39:51Z",
      "summary": "A new proposal would include Bible stories in required reading lists for more than 5 million public school students in Texas",
      "content": "<h2>What to know about the push to make Bible stories required reading in Texas public schools</h2> <p>A new proposal would include Bible stories in required reading lists for more than 5 million public school students in Texas</p> <p>AUSTIN, Texas -- Texas would make Bible stories required reading for more than 5 million public school students under a proposal that has reignited debate over widening efforts in the U.S. to put more religion in classrooms.</p> <p>A final vote by the Republican-controlled Texas State Board of Education on whether to approve the plan is set for Friday. Last year, Texas became the largest state to require every classroom to display the Ten Commandments.</p> <p>The proposal has drawn fierce opposition. Critics argue the changes violate the constitutional separation of church and state, inflate the role of Christianity in the nation\u2019s history and favor it over other religions. Supporters say Judeo-Christian traditions were fundamental to the nation\u2019s founding and that should be reflected in the public school curriculum.</p> <p>Here's what to know about the proposal and the broader fight over religion in public schools in the U.S.</p> <p>President Donald Trump has pledged to protect and expand religious expression in public schools nationwide, and Texas \u2014 a red state that is home to about one in 10 of all U.S. public school students \u2014 often sets the agenda.</p> <p>In 2023, Texas became the first state to allow the hiring of chaplains to counsel students, and the following year, the board narrowly approved an optional Bible-infused curriculum for elementary schools. Last year, Republican lawmakers required public schools to display the Ten Commandments, a measure recently upheld by a federal appeals court.</p> <p>Texas has about 5.5 million public school students from kindergarten through high school. If approved by the board, the required reading list would take effect in 2030.</p> <p>\u201cWe need to focus on what our nation was founded on and not apologize for that,\u201d Susan Perez, founder of the Citizens for Education Reform, told the education board during testimony over the proposal. \u201cIt is the truth and we should not be afraid.\u201d</p> <p>Picture-book stories for elementary students including \u201cNoah\u2019s Ark,\u201d \u201cDavid and Goliath\u201d and \u201cDaniel and the Lion\u2019s Den\u201d are on the required reading list. By fourth grade, students would encounter passages about Jesus in the New Testament.</p> <p>By middle school, students would be expected to read several passages about Jesus, including passages from his most famous sermon, and another where he instructs people to cast aside earthly anxiety and seek the kingdom of God. Another would connect a reading from the Book of Lamentations and its themes of the destruction of Jerusalem with readings about the Holocaust.</p> <p>In high school, students would read the parable of the prodigal son, portions of the Book of Job, and the story of Adam and Eve.</p> <p>Some education observers said Texas may be the first state to enact a required reading list, with the added layer of mandated religious text.</p> <p>Antero Garcia, president of the National Council of Teachers of English and a Stanford University professor, said he doesn\u2019t know of any other state that has such a list. Educators at the district and school level usually choose what texts their students will read, Garcia said.</p> <p>Kasey Meehan, director of PEN America\u2019s Freedom to Read program, said she believes such a mandated reading list would be \u201cunique\u201d to Texas.</p> <p>\u201cI think there\u2019s lots of state lists that exist that are like advised readings, suggested readings,\u201d she said.</p> <p>The required readings rely heavily on the King James Bible, one of the most popular translations, and more recent evangelical translations that critics argue lean too heavily on Christian interpretations of the texts.</p> <p>Other critics question whether religious stories should be taught at all in schools attended by thousands of children of Muslim, Buddhist, Hindu and other faiths, and others who identify as atheist or agnostic.</p> <p>\u201cI do think that it\u2019s disturbing that there are no texts from other religious traditions that are included,\u201d said Frank Strong, an English and journalism teacher and co-founder of the student advocacy group Texas Freedom to Read.</p> <p>___</p> <p>Stengle reported from Dallas.</p>",
      "category": "us_news",
      "image": "https://s.abcnews.com/images/US/abc_news_default_2000x2000_update_4x3t_384.jpg"
    },
    {
      "id": "edb99dc074473fe900616afac5e7902ff038ac6064377a4eca4d6728013c67ae",
      "title": "Charges against New York ex-Mayor Eric Adams' top aide are just the latest probe of his inner circle",
      "source": "ABC News \u2014 US Headlines",
      "source_id": "abc_us",
      "published_at": "2026-06-24T21:39:48Z",
      "summary": "Federal bribery charges against former New York Mayor Eric Adams' onetime chief of staff are just the latest allegations against members of the ex-mayor's inner circle",
      "content": "<h2>Charges against New York ex-Mayor Eric Adams' top aide are just the latest probe of his inner circle</h2> <p>Federal bribery charges against former New York Mayor Eric Adams' onetime chief of staff are just the latest allegations against members of the ex-mayor's inner circle</p> <p>NEW YORK -- In his four years as New York mayor, Eric Adams' administration was roiled by corruption probes that led to early-morning FBI searches, resignations of top officials and indictments that alleged a rampant culture of pay-to-play politics at the highest levels of City Hall.</p> <p>Even with Adams now far from elected office and facing no charges himself, that saga continues.</p> <p>On Wednesday his former chief of staff, Frank Carone, was arrested on federal charges alleging that he accepted $120,000 in bribes in exchange for steering a multimillion-dollar migrant shelter contract to a Queens hotel. Three others, including Carone\u2019s brother, were also indicted. All have pleaded not guilty.</p> <p>Another of Adams' closest allies, Ingrid Lewis-Martin, is still fighting separate bribery charges, which include allegations that she exchanged political favors for cash, diamond earrings and a speaking role on a TV show.</p> <p>And Adams himself was indicted on bribery charges in 2024, accused of taking illegal campaign contributions from Turkish officials and providing political favors to them in return. Adams, a Democrat, denied any wrongdoing and those charges were later dropped at the behest of the Trump administration.</p> <p>Here is a look at some of the criminal investigations that cast a pall over the nation's largest city during Adams' tumultuous tenure and its aftermath:</p> <p>Soon after Adams took office in January 2022, federal agents quietly began a corruption investigation into his campaign. It spilled into public view in the fall of 2023, when authorities seized his phones as he was leaving an event. A year later, federal prosecutors brought fraud and bribery charges against him.</p> <p>The indictment accused Adams of allowing Turkish officials and other businesspeople to buy his influence with illegal campaign contributions and steep discounts on overseas trips. Among the favors he allegedly provided in return was accelerating the opening of Turkey's diplomatic building in New York, prosecutors said.</p> <p>Adams denied wrongdoing and insisted, without evidence, that the Biden administration had politically targeted his administration because of his criticism of its immigration policy.</p> <p>But soon after President Donald Trump returned to the White House in early 2025, Justice Department leadership ordered Manhattan federal prosecutors to drop the case, arguing that it was hindering the mayor\u2019s ability to assist Trump's immigration crackdown.</p> <p>The investigation severely wounded Adams' efforts last year to seek reelection. He skipped the Democratic primary and got on the ballot as an independent, but eventually ended his campaign early.</p> <p>As former chief adviser, Lewis-Martin was perhaps the only city official with more direct access to Adams than Carone.</p> <p>In 2024 she too was indicted for allegedly trading her influence for bribes worth more than $100,000 from those with business before the city. Lewis-Martin has denied wrongdoing.</p> <p>In one instance, prosecutors said, Lewis-Martin agreed to quash a planned bike lane near a Brooklyn soundstage at the request of the studio\u2019s owners in exchange for perks including a promised role on the police drama \u201cBlue Bloods.\u201d</p> <p>In a separate scheme, prosecutors said, she accepted diamond earrings and cash from two real estate developers and then helped to speed up approvals of their projects, at times overriding safety concerns from city regulators.</p> <p>Her attorney Arthur Aidala \u2014 who is also representing Carone \u2014 has said she was simply helping constituents cut through the city\u2019s thick red tape.</p> <p>The case against Lewis-Martin was brought by the Manhattan District Attorney Alvin Bragg, and a hearing is scheduled for Thursday.</p> <p>Many who departed Adams' administration under a cloud of scandal \u2014 often after having their devices seized and homes searched by federal agents \u2014 have not faced charges.</p> <p>Among them: an adviser to the Chinese community who handed a potato chip bag full of cash to a reporter after an Adams campaign event; the former police commissioner, whose twin brother was accused of extortion by a Brooklyn bar owner; and Adams\u2019 schools chancellor and deputy mayor, also brothers, whose third brother ran a consulting firm that connected clients with city officials.</p> <p>Each has denied wrongdoing, and none has been charged with a crime.</p> <p>Federal authorities have declined to disclose the purpose of their searches and whether any of the investigations remain active.</p> <p>Even after the charges against Adams were dropped, prosecutors continued to pursue cases against some of the lower-level operatives involved in the indictment.</p> <p>One, a Brooklyn real estate magnate, was sentenced to a year of probation last summer after pleading guilty to working with a Turkish government official to funnel illegal donations to Adams' 2021 campaign.</p> <p>And in November an Adams aide who served as his liaison to the city's Muslim communities was sentenced to three years of probation for soliciting illegal campaign funds.</p> <p>Before handing down that sentence, Judge Dale Ho, who also presided over the case against Adams that was dismissed, likened the mayor's absence to an \u201celephant in the room.\u201d</p> <p>\u201cThere\u2019s a notable absence here of the person at the apex of the pyramid,\u201d he said.</p> <p>___</p> <p>Collins reported from Hartford, Connecticut.</p>",
      "category": "us_news",
      "image": "https://s.abcnews.com/images/US/wirestory_d51f7753d13388ec70e948318468ae79_4x3_384.jpg"
    },
    {
      "id": "362bc400778e57311417ea55a1d8c822f003e92e9fbe3536b3f8fa1f4a169983",
      "title": "All 32 of the nation's biggest banks clear the Fed's annual 'stress test'",
      "source": "ABC News \u2014 US Headlines",
      "source_id": "abc_us",
      "published_at": "2026-06-24T21:39:46Z",
      "summary": "The Federal Reserve says that all 32 of the nation's biggest banks have passed its annual stress test",
      "content": "<h2>All 32 of the nation's biggest banks clear the Fed's annual 'stress test'</h2> <p>The Federal Reserve says that all 32 of the nation's biggest banks have passed its annual stress test</p> <p>NEW YORK -- All 32 of the nation's biggest banks passed the Federal Reserve's annual \u201cstress test\u201d of the financial system, the central bank said Wednesday, a sign that the banking system would remain healthy even if a major economic contraction occurred.</p> <p>The annual stress test measures whether a bank\u2019s capital, a financial cushion it uses to absorb losses, would remain at healthy levels even after hundreds of billions of dollars in projected losses. The tests are required under the Dodd-Frank Act, the law passed after the 2008 financial crisis that nearly brought down the global financial system.</p> <p>The 2026 scenario that the Fed used is similar to the one they used last year. In the Fed's scenario, unemployment would rise from 5.5% to 10% and the U.S. economy would contract 4.6%. Housing prices would fall 30% from their current levels and the stock market would plunge 58%.</p> <p>The scenario would result in the nation\u2019s 32 biggest banks facing $708 billion in loan losses, but the overall capital ratio of these banks would fall only 1.6 percentage points, from 12.8% to 11.2%. By law and regulation, these large banks' common equity Tier 1 capital ratio must remain above 4.5%, plus additional buffers that vary by bank.</p> <p>The stress test applied only to the nation's most systematically important banks, those whose failures would bring significant turmoil to the financial system.</p> <p>A bank that performed poorly on the stress test could face higher capital requirements, which could limit its ability to pay dividends or buy back stock. Banks typically announce their plans for dividends and share repurchases after the Fed releases the stress-test results. Shortly after the Fed's announcement, JPMorgan Chase said it would increase its quarterly dividend to $1.65 a share from $1.50 a share, and intends to buy back an additional $50 billion in stock.</p>",
      "category": "us_news",
      "image": "https://s.abcnews.com/images/US/wirestory_dbb5f33becf7240fbb9a85fa2befd8f3_4x3_384.jpg"
    },
    {
      "id": "9308757fce53caef4d0ce05270997d418fd12eba9c5199ca3ea31067c40a2c28",
      "title": "White House asks Congress for $87.6B for Iran war, aid to US farmers and responding to Ebola crisis",
      "source": "ABC News \u2014 US Headlines",
      "source_id": "abc_us",
      "published_at": "2026-06-24T21:39:40Z",
      "summary": "The White House has formally requested $87.6 billion mostly to replenish the Pentagon after the U.S. war against Iran, submitting the request to Congress at a politically difficult time as a majority of lawmakers have objected to any further military a...",
      "content": "<h2>White House asks Congress for $87.6B for Iran war, aid to US farmers and responding to Ebola crisis</h2> <p>The White House has formally requested $87.6 billion mostly to replenish the Pentagon after the U.S. war against Iran, submitting the request to Congress at a politically difficult time as a majority of lawmakers have objected to any further military a...</p> <p>WASHINGTON -- The White House has formally requested $87.6 billion mostly to replenish the Pentagon after the U.S. war against Iran, submitting the request to Congress at a politically difficult time as a majority of lawmakers have objected to any further military action. The Office of Management and Budget sent the supplemental spending request Wednesday. It arrived just hours after President Donald Trump assailed Republican senators during a private lunch \u2014 engaging in a shouting match with one \u2014 over their votes to approve a war powers resolution that would halt further hostilities. The request is mostly for Operation Epic Fury, but it also includes a range of other items including aid to American farmers, help for the Ebola crisis in Africa and other needs closer to home, including restoration projects in Washington, D.C. \u201cI urge the Congress to take action on these important and urgent requests as soon as possible,\u201d said OMB Director Russ Vought in a letter to House Speaker Mike Johnson. The administration said it is requesting $67 billion for the Department of Defense for what it said were urgent needs related to the war against Iran, including \u201cfunding for military personnel and readiness expenses, operational costs to rebuild stocks.\u201d</p>",
      "category": "us_news",
      "image": "https://s.abcnews.com/images/US/wirestory_c0cbd21df91c48fa821fc21e021d8831_4x3_384.jpg"
    }
  ]
}
